{
    "bpp_loss": 2.6688270604667754,
    "bpp": 0.003211388221153846,
    "ppl": {
        "wikitext2": 7.994186878204346,
        "c4": 11.452549934387207
    },
    "num_pixels": 6979321856,
    "config": {
        "quant_args": {
            "seed": 0,
            "num_cpu_threads": 8,
            "batch_size": 8,
            "devset_size": 384,
            "ctx_size": 4096,
            "save_path": "../hf_model_comp/comp_qtip/ckpt/meta-llama--Meta-Llama-3-8B/noLN(cnorm)_ql_cnorm/lmbda50",
            "in_hess_path": "../Wparam_dataset/quip_hess/llama3_8b_6144",
            "in_hess_eig_path": null,
            "whiten": false,
            "base_model": "../Wparam_dataset/hf_model/meta-llama--Meta-Llama-3-8B",
            "sigma_reg": 0.01,
            "sigma_reg2": 0.01,
            "scale_override": -1,
            "use_fp64": false,
            "no_use_buffered": false,
            "sample_proc": 1,
            "lowmem_ldlq": false,
            "ft_lr": 3e-06,
            "ft_bs": 4,
            "ft_update_freq": 1,
            "ft_epochs": 0,
            "ft_valid_freq": 1,
            "ft_valid_size": 128.0,
            "ft_early_stop": 5,
            "ft_grad_ckpt": false,
            "skip_list": null,
            "bundle": true,
            "ql": true,
            "ql_path": null,
            "hesseigen": null,
            "gptq": false,
            "ldlq": false,
            "comp_model_path": "/home/jgryu/workspace/weight_compression/NWC/checkpoint2/nwc_ql/8b_cnormed_col1024_seq_ql_random/rdloss_ql_size16_encdim512_M16_Q4_nRB4R0_m0_batch_size2048_total_iter200000_lr0.0001_seed100/noLN_cnormed/lmbda50_/best_loss_model_loss_3.88874_bpp_4.60778_MSE_0.01646_total_iter_47500.pth.tar",
            "direction": "col",
            "comp_batch_size": -1,
            "quip_tune_iters": 0,
            "rescale_WH": false,
            "rescale_WH_2": false,
            "incoh_mode": "none",
            "lora_rank": 0,
            "ql_invH": false,
            "use_train_scale": false,
            "layerwise_cdt": false,
            "ft_comp_model": false,
            "ft_comp_model2": false,
            "ft_comp_lmbda": null,
            "ft_comp_ep": null,
            "ft_comp_steps": null,
            "ft_comp_learning_rate": 0.0001,
            "ft_comp_aux_learning_rate": 0.001,
            "ft_train": false,
            "ft_train_dec": false,
            "ql_search": false,
            "ql_search_layer_name": "q,k,v,o,up,gate,down",
            "ql_search_layer_idx": null,
            "ql_search_value": null,
            "ql_search_r": null,
            "ql_tuned": false,
            "layer_normalize": false,
            "channelwise_scale": false,
            "row_normalize": false,
            "row_normalize2": false,
            "col_normalize": true,
            "code_optim": false,
            "code_optim_it": false,
            "code_optim_lr": 0.005,
            "code_optim_lmbda": null,
            "code_optim_test": false,
            "code_optim_model": "nwc_ql_sga",
            "optim_qs": false,
            "Q": 4,
            "use_codes": false,
            "qmap_uniform": null,
            "qmap_hessian": false,
            "qmap_hessian_ql": false,
            "qmap_alpha": false,
            "qmap_optim_iter": 5,
            "qmap_optim": false,
            "cnorm_optim": false,
            "rnorm_optim": false,
            "ft_rnorm": false,
            "ft_scale_cond0": false,
            "ft_metadata": false,
            "ft_Wr": false,
            "ft_y": false,
            "ft_bpp_loss": false,
            "scaleH": false,
            "smooth_scaleH_alpha": null,
            "lb_scaleH": null,
            "scaleHinv": false,
            "scale_std": null,
            "ste": false,
            "handcraft_mode": null,
            "quant_method": null,
            "group_sz": -1,
            "jp_quality": -1,
            "bpg_quality": -1,
            "webp_quality": -1,
            "nic_model": null,
            "nic_checkpoint": null,
            "nic_patch_size": -1,
            "nic_norm_patch_size": -1,
            "illm_quality": -1,
            "scale_cond0": false,
            "scale_cond_ub": null,
            "scale_cond": false,
            "fp_iter": false,
            "fp_iter_max": null,
            "fp_tol": 1e-05,
            "perlayer_ft_epochs": 0,
            "perlayer_ft_bs": 0,
            "perlayer_ft_lmbda": 0,
            "initialize_codec": false,
            "loss": "rdloss_ql",
            "use_hyper": false
        },
        "model_config": {
            "vocab_size": 128256,
            "max_position_embeddings": 8192,
            "hidden_size": 4096,
            "intermediate_size": 14336,
            "num_hidden_layers": 32,
            "num_attention_heads": 32,
            "num_key_value_heads": 8,
            "hidden_act": "silu",
            "initializer_range": 0.02,
            "rms_norm_eps": 1e-05,
            "pretraining_tp": 1,
            "use_cache": true,
            "rope_theta": 500000.0,
            "rope_scaling": null,
            "attention_bias": false,
            "attention_dropout": 0.0,
            "mlp_bias": false,
            "head_dim": 128,
            "return_dict": true,
            "output_hidden_states": false,
            "torchscript": false,
            "dtype": "float32",
            "pruned_heads": {},
            "tie_word_embeddings": false,
            "chunk_size_feed_forward": 0,
            "is_encoder_decoder": false,
            "is_decoder": false,
            "cross_attention_hidden_size": null,
            "add_cross_attention": false,
            "tie_encoder_decoder": false,
            "architectures": [
                "LlamaForCausalLM"
            ],
            "finetuning_task": null,
            "id2label": {
                "0": "LABEL_0",
                "1": "LABEL_1"
            },
            "label2id": {
                "LABEL_0": 0,
                "LABEL_1": 1
            },
            "task_specific_params": null,
            "problem_type": null,
            "tokenizer_class": null,
            "prefix": null,
            "bos_token_id": 128000,
            "pad_token_id": null,
            "eos_token_id": 128001,
            "sep_token_id": null,
            "decoder_start_token_id": null,
            "max_length": 20,
            "min_length": 0,
            "do_sample": false,
            "early_stopping": false,
            "num_beams": 1,
            "temperature": 1.0,
            "top_k": 50,
            "top_p": 1.0,
            "typical_p": 1.0,
            "repetition_penalty": 1.0,
            "length_penalty": 1.0,
            "no_repeat_ngram_size": 0,
            "encoder_no_repeat_ngram_size": 0,
            "bad_words_ids": null,
            "num_return_sequences": 1,
            "output_scores": false,
            "return_dict_in_generate": false,
            "forced_bos_token_id": null,
            "forced_eos_token_id": null,
            "remove_invalid_values": false,
            "exponential_decay_length_penalty": null,
            "suppress_tokens": null,
            "begin_suppress_tokens": null,
            "num_beam_groups": 1,
            "diversity_penalty": 0.0,
            "_name_or_path": "../Wparam_dataset/hf_model/meta-llama--Meta-Llama-3-8B",
            "transformers_version": "4.57.1",
            "model_type": "llama",
            "tf_legacy_loss": false,
            "use_bfloat16": false,
            "comp_params": {
                "ft_rnorm": false,
                "row_normalize": false,
                "col_normalize": true
            },
            "output_attentions": false
        }
    },
    "0_q.pt": {
        "W_hat": null,
        "bpp_loss": 2.6006765365600586,
        "bpp": 0.0,
        "proxy_err": 0.0014189179055392742,
        "err": 408.78253173828125,
        "tr(WHW.T)": 288094.5625,
        "mse": 1.007837909128284e-05,
        "bpp_sum": 73728,
        "bpp_loss_sum": 43705840.0,
        "direction": "col",
        "num_pixels": 16777216
    },
    "0_k.pt": {
        "W_hat": null,
        "bpp_loss": 2.62569522857666,
        "bpp": 0.0,
        "proxy_err": 0.002038199920207262,
        "err": 204.18836975097656,
        "tr(WHW.T)": 100180.734375,
        "mse": 2.0597792172338814e-05,
        "bpp_sum": 73728,
        "bpp_loss_sum": 11086692.0,
        "direction": "col",
        "num_pixels": 4194304
    },
    "0_v.pt": {
        "W_hat": null,
        "bpp_loss": 2.653585910797119,
        "bpp": 0.0,
        "proxy_err": 0.02519131451845169,
        "err": 1.533819556236267,
        "tr(WHW.T)": 60.8868408203125,
        "mse": 1.7031878769557807e-06,
        "bpp_sum": 73728,
        "bpp_loss_sum": 11203674.0,
        "direction": "col",
        "num_pixels": 4194304
    },
    "0_o.pt": {
        "W_hat": null,
        "bpp_loss": 2.6480095386505127,
        "bpp": 0.0,
        "proxy_err": 0.008238197304308414,
        "err": 25.72968292236328,
        "tr(WHW.T)": 3123.2177734375,
        "mse": 2.1207358713581925e-06,
        "bpp_sum": 73728,
        "bpp_loss_sum": 44499956.0,
        "direction": "col",
        "num_pixels": 16777216
    },
    "0_up.pt": {
        "W_hat": null,
        "bpp_loss": 2.6700507572719028,
        "bpp": 0.0,
        "proxy_err": 0.026097437366843224,
        "err": 232.90530395507812,
        "tr(WHW.T)": 8924.451171875,
        "mse": 4.285256636649137e-06,
        "bpp_sum": 73728,
        "bpp_loss_sum": 156859792.0,
        "direction": "col",
        "num_pixels": 58720256
    },
    "0_gate.pt": {
        "W_hat": null,
        "bpp_loss": 2.669759750366211,
        "bpp": 0.0,
        "proxy_err": 0.018179314211010933,
        "err": 286.8453369140625,
        "tr(WHW.T)": 15778.6669921875,
        "mse": 5.142708232597215e-06,
        "bpp_sum": 73728,
        "bpp_loss_sum": 156842704.0,
        "direction": "col",
        "num_pixels": 58720256
    },
    "0_down.pt": {
        "W_hat": null,
        "bpp_loss": 2.6649927411760603,
        "bpp": 0.0,
        "proxy_err": 0.018244825303554535,
        "err": 197.37625122070312,
        "tr(WHW.T)": 10818.2041015625,
        "mse": 4.265802999725565e-06,
        "bpp_sum": 258048,
        "bpp_loss_sum": 156747104.0,
        "direction": "col",
        "num_pixels": 58720256
    },
    "1_q.pt": {
        "W_hat": null,
        "bpp_loss": 2.6167688369750977,
        "bpp": 0.0,
        "proxy_err": 0.0013177929213270545,
        "err": 190.85133361816406,
        "tr(WHW.T)": 144826.5,
        "mse": 1.235705531144049e-05,
        "bpp_sum": 73728,
        "bpp_loss_sum": 43975824.0,
        "direction": "col",
        "num_pixels": 16777216
    },
    "1_k.pt": {
        "W_hat": null,
        "bpp_loss": 2.6202573776245117,
        "bpp": 0.0,
        "proxy_err": 0.001716632628813386,
        "err": 129.67279052734375,
        "tr(WHW.T)": 75539.046875,
        "mse": 2.41309535340406e-05,
        "bpp_sum": 73728,
        "bpp_loss_sum": 11063884.0,
        "direction": "col",
        "num_pixels": 4194304
    },
    "1_v.pt": {
        "W_hat": null,
        "bpp_loss": 2.663581371307373,
        "bpp": 0.0,
        "proxy_err": 0.01880299672484398,
        "err": 2.05086088180542,
        "tr(WHW.T)": 109.07096099853516,
        "mse": 2.4069208848231938e-06,
        "bpp_sum": 73728,
        "bpp_loss_sum": 11245598.0,
        "direction": "col",
        "num_pixels": 4194304
    },
    "1_o.pt": {
        "W_hat": null,
        "bpp_loss": 2.637407064437866,
        "bpp": 0.0,
        "proxy_err": 0.018039366230368614,
        "err": 35.787071228027344,
        "tr(WHW.T)": 1983.83203125,
        "mse": 2.743391178228194e-06,
        "bpp_sum": 73728,
        "bpp_loss_sum": 44322076.0,
        "direction": "col",
        "num_pixels": 16777216
    },
    "1_up.pt": {
        "W_hat": null,
        "bpp_loss": 2.6698431287493025,
        "bpp": 0.0,
        "proxy_err": 0.02938024513423443,
        "err": 241.82351684570312,
        "tr(WHW.T)": 8230.8203125,
        "mse": 4.4294647523202e-06,
        "bpp_sum": 73728,
        "bpp_loss_sum": 156847600.0,
        "direction": "col",
        "num_pixels": 58720256
    },
    "1_gate.pt": {
        "W_hat": null,
        "bpp_loss": 2.670091356549944,
        "bpp": 0.0,
        "proxy_err": 0.021124226972460747,
        "err": 294.7329406738281,
        "tr(WHW.T)": 13952.365234375,
        "mse": 5.327160124579677e-06,
        "bpp_sum": 73728,
        "bpp_loss_sum": 156862176.0,
        "direction": "col",
        "num_pixels": 58720256
    },
    "1_down.pt": {
        "W_hat": null,
        "bpp_loss": 2.66788455418178,
        "bpp": 0.0,
        "proxy_err": 0.0026694396510720253,
        "err": 37.31359100341797,
        "tr(WHW.T)": 13978.0615234375,
        "mse": 4.398076271172613e-06,
        "bpp_sum": 258048,
        "bpp_loss_sum": 156916912.0,
        "direction": "col",
        "num_pixels": 58720256
    },
    "2_q.pt": {
        "W_hat": null,
        "bpp_loss": 2.6301491260528564,
        "bpp": 0.0,
        "proxy_err": 0.0037661867681890726,
        "err": 156.20318603515625,
        "tr(WHW.T)": 41475.15625,
        "mse": 1.1657734830805566e-05,
        "bpp_sum": 73728,
        "bpp_loss_sum": 44200308.0,
        "direction": "col",
        "num_pixels": 16777216
    },
    "2_k.pt": {
        "W_hat": null,
        "bpp_loss": 2.6286277770996094,
        "bpp": 0.0,
        "proxy_err": 0.0048190029338002205,
        "err": 108.97949981689453,
        "tr(WHW.T)": 22614.533203125,
        "mse": 2.691431473067496e-05,
        "bpp_sum": 73728,
        "bpp_loss_sum": 11098992.0,
        "direction": "col",
        "num_pixels": 4194304
    },
    "2_v.pt": {
        "W_hat": null,
        "bpp_loss": 2.659388303756714,
        "bpp": 0.0,
        "proxy_err": 0.020674491301178932,
        "err": 3.2243833541870117,
        "tr(WHW.T)": 155.95950317382812,
        "mse": 1.6936744486883981e-06,
        "bpp_sum": 73728,
        "bpp_loss_sum": 11228011.0,
        "direction": "col",
        "num_pixels": 4194304
    },
    "2_o.pt": {
        "W_hat": null,
        "bpp_loss": 2.658823013305664,
        "bpp": 0.0,
        "proxy_err": 0.014376087114214897,
        "err": 28.28240203857422,
        "tr(WHW.T)": 1967.3226318359375,
        "mse": 2.31843841902446e-06,
        "bpp_sum": 73728,
        "bpp_loss_sum": 44681376.0,
        "direction": "col",
        "num_pixels": 16777216
    },
    "2_up.pt": {
        "W_hat": null,
        "bpp_loss": 2.671440396990095,
        "bpp": 0.0,
        "proxy_err": 0.032281577587127686,
        "err": 245.35528564453125,
        "tr(WHW.T)": 7600.47412109375,
        "mse": 4.397579232318094e-06,
        "bpp_sum": 73728,
        "bpp_loss_sum": 156941392.0,
        "direction": "col",
        "num_pixels": 58720256
    },
    "2_gate.pt": {
        "W_hat": null,
        "bpp_loss": 2.6726477486746654,
        "bpp": 0.0,
        "proxy_err": 0.021055487915873528,
        "err": 318.21826171875,
        "tr(WHW.T)": 15113.31640625,
        "mse": 5.637598860630533e-06,
        "bpp_sum": 73728,
        "bpp_loss_sum": 157012288.0,
        "direction": "col",
        "num_pixels": 58720256
    },
    "2_down.pt": {
        "W_hat": null,
        "bpp_loss": 2.6703763689313615,
        "bpp": 0.0,
        "proxy_err": 0.027903247624635696,
        "err": 215.60073852539062,
        "tr(WHW.T)": 7726.7255859375,
        "mse": 4.421509402163792e-06,
        "bpp_sum": 258048,
        "bpp_loss_sum": 157063232.0,
        "direction": "col",
        "num_pixels": 58720256
    },
    "3_q.pt": {
        "W_hat": null,
        "bpp_loss": 2.6455929279327393,
        "bpp": 0.0,
        "proxy_err": 0.0035537444055080414,
        "err": 169.0762481689453,
        "tr(WHW.T)": 47576.9296875,
        "mse": 1.182592586701503e-05,
        "bpp_sum": 73728,
        "bpp_loss_sum": 44459412.0,
        "direction": "col",
        "num_pixels": 16777216
    },
    "3_k.pt": {
        "W_hat": null,
        "bpp_loss": 2.6416397094726562,
        "bpp": 0.0,
        "proxy_err": 0.003956699278205633,
        "err": 103.56468200683594,
        "tr(WHW.T)": 26174.513671875,
        "mse": 2.742624383245129e-05,
        "bpp_sum": 73728,
        "bpp_loss_sum": 11153568.0,
        "direction": "col",
        "num_pixels": 4194304
    },
    "3_v.pt": {
        "W_hat": null,
        "bpp_loss": 2.661267042160034,
        "bpp": 0.0,
        "proxy_err": 0.02350885421037674,
        "err": 6.801891326904297,
        "tr(WHW.T)": 289.3331604003906,
        "mse": 2.3631037038285285e-06,
        "bpp_sum": 73728,
        "bpp_loss_sum": 11235891.0,
        "direction": "col",
        "num_pixels": 4194304
    },
    "3_o.pt": {
        "W_hat": null,
        "bpp_loss": 2.666844606399536,
        "bpp": 0.0,
        "proxy_err": 0.022282781079411507,
        "err": 41.38264465332031,
        "tr(WHW.T)": 1857.157958984375,
        "mse": 3.059635901081492e-06,
        "bpp_sum": 73728,
        "bpp_loss_sum": 44815956.0,
        "direction": "col",
        "num_pixels": 16777216
    },
    "3_up.pt": {
        "W_hat": null,
        "bpp_loss": 2.671039581298828,
        "bpp": 0.0,
        "proxy_err": 0.030970819294452667,
        "err": 233.41049194335938,
        "tr(WHW.T)": 7536.46484375,
        "mse": 4.227486442687223e-06,
        "bpp_sum": 73728,
        "bpp_loss_sum": 156917856.0,
        "direction": "col",
        "num_pixels": 58720256
    },
    "3_gate.pt": {
        "W_hat": null,
        "bpp_loss": 2.6707510266985213,
        "bpp": 0.0,
        "proxy_err": 0.0170755572617054,
        "err": 356.6119079589844,
        "tr(WHW.T)": 20884.349609375,
        "mse": 6.346822374325711e-06,
        "bpp_sum": 73728,
        "bpp_loss_sum": 156900912.0,
        "direction": "col",
        "num_pixels": 58720256
    },
    "3_down.pt": {
        "W_hat": null,
        "bpp_loss": 2.6720875331333707,
        "bpp": 0.0,
        "proxy_err": 0.0306775514036417,
        "err": 214.70022583007812,
        "tr(WHW.T)": 6998.6103515625,
        "mse": 4.21344975620741e-06,
        "bpp_sum": 258048,
        "bpp_loss_sum": 157163712.0,
        "direction": "col",
        "num_pixels": 58720256
    },
    "4_q.pt": {
        "W_hat": null,
        "bpp_loss": 2.637141466140747,
        "bpp": 0.0,
        "proxy_err": 0.0030937145929783583,
        "err": 155.04107666015625,
        "tr(WHW.T)": 50114.859375,
        "mse": 1.1483034541015513e-05,
        "bpp_sum": 73728,
        "bpp_loss_sum": 44317620.0,
        "direction": "col",
        "num_pixels": 16777216
    },
    "4_k.pt": {
        "W_hat": null,
        "bpp_loss": 2.6438069343566895,
        "bpp": 0.0,
        "proxy_err": 0.0033551861997693777,
        "err": 98.3135757446289,
        "tr(WHW.T)": 29301.97265625,
        "mse": 2.632967516547069e-05,
        "bpp_sum": 73728,
        "bpp_loss_sum": 11162658.0,
        "direction": "col",
        "num_pixels": 4194304
    },
    "4_v.pt": {
        "W_hat": null,
        "bpp_loss": 2.659478187561035,
        "bpp": 0.0,
        "proxy_err": 0.023316437378525734,
        "err": 6.652345657348633,
        "tr(WHW.T)": 285.30712890625,
        "mse": 2.7658491035253974e-06,
        "bpp_sum": 73728,
        "bpp_loss_sum": 11228388.0,
        "direction": "col",
        "num_pixels": 4194304
    },
    "4_o.pt": {
        "W_hat": null,
        "bpp_loss": 2.658217668533325,
        "bpp": 0.0,
        "proxy_err": 0.0295327827334404,
        "err": 38.311344146728516,
        "tr(WHW.T)": 1297.248046875,
        "mse": 3.2256555186904734e-06,
        "bpp_sum": 73728,
        "bpp_loss_sum": 44671220.0,
        "direction": "col",
        "num_pixels": 16777216
    },
    "4_up.pt": {
        "W_hat": null,
        "bpp_loss": 2.6680150713239397,
        "bpp": 0.0,
        "proxy_err": 0.02925817295908928,
        "err": 216.02734375,
        "tr(WHW.T)": 7383.4873046875,
        "mse": 4.009677468275186e-06,
        "bpp_sum": 73728,
        "bpp_loss_sum": 156740256.0,
        "direction": "col",
        "num_pixels": 58720256
    },
    "4_gate.pt": {
        "W_hat": null,
        "bpp_loss": 2.671949931553432,
        "bpp": 0.0,
        "proxy_err": 0.013323308899998665,
        "err": 388.1209716796875,
        "tr(WHW.T)": 29130.974609375,
        "mse": 7.057315087877214e-06,
        "bpp_sum": 73728,
        "bpp_loss_sum": 156971312.0,
        "direction": "col",
        "num_pixels": 58720256
    },
    "4_down.pt": {
        "W_hat": null,
        "bpp_loss": 2.6708243233816966,
        "bpp": 0.0,
        "proxy_err": 0.0330866314470768,
        "err": 211.6129150390625,
        "tr(WHW.T)": 6395.72265625,
        "mse": 3.993283826275729e-06,
        "bpp_sum": 258048,
        "bpp_loss_sum": 157089536.0,
        "direction": "col",
        "num_pixels": 58720256
    },
    "5_q.pt": {
        "W_hat": null,
        "bpp_loss": 2.632986545562744,
        "bpp": 0.0,
        "proxy_err": 0.004245738498866558,
        "err": 152.81101989746094,
        "tr(WHW.T)": 35991.625,
        "mse": 1.1396929039619863e-05,
        "bpp_sum": 73728,
        "bpp_loss_sum": 44247912.0,
        "direction": "col",
        "num_pixels": 16777216
    },
    "5_k.pt": {
        "W_hat": null,
        "bpp_loss": 2.6365513801574707,
        "bpp": 0.0,
        "proxy_err": 0.004375465214252472,
        "err": 100.62586975097656,
        "tr(WHW.T)": 22997.75390625,
        "mse": 2.6546909793978557e-05,
        "bpp_sum": 73728,
        "bpp_loss_sum": 11132226.0,
        "direction": "col",
        "num_pixels": 4194304
    },
    "5_v.pt": {
        "W_hat": null,
        "bpp_loss": 2.6628029346466064,
        "bpp": 0.0,
        "proxy_err": 0.02190631628036499,
        "err": 4.574474334716797,
        "tr(WHW.T)": 208.81988525390625,
        "mse": 1.9094952676823596e-06,
        "bpp_sum": 73728,
        "bpp_loss_sum": 11242333.0,
        "direction": "col",
        "num_pixels": 4194304
    },
    "5_o.pt": {
        "W_hat": null,
        "bpp_loss": 2.669290065765381,
        "bpp": 0.0,
        "proxy_err": 0.030996104702353477,
        "err": 32.71907043457031,
        "tr(WHW.T)": 1055.5865478515625,
        "mse": 2.7348864932719152e-06,
        "bpp_sum": 73728,
        "bpp_loss_sum": 44856984.0,
        "direction": "col",
        "num_pixels": 16777216
    },
    "5_up.pt": {
        "W_hat": null,
        "bpp_loss": 2.669612067086356,
        "bpp": 0.0,
        "proxy_err": 0.028345996513962746,
        "err": 217.02923583984375,
        "tr(WHW.T)": 7656.43359375,
        "mse": 4.063600954395952e-06,
        "bpp_sum": 73728,
        "bpp_loss_sum": 156834032.0,
        "direction": "col",
        "num_pixels": 58720256
    },
    "5_gate.pt": {
        "W_hat": null,
        "bpp_loss": 2.675225394112723,
        "bpp": 0.0,
        "proxy_err": 0.01266900822520256,
        "err": 384.97247314453125,
        "tr(WHW.T)": 30386.947265625,
        "mse": 7.048255611152854e-06,
        "bpp_sum": 73728,
        "bpp_loss_sum": 157163648.0,
        "direction": "col",
        "num_pixels": 58720256
    },
    "5_down.pt": {
        "W_hat": null,
        "bpp_loss": 2.670816421508789,
        "bpp": 0.0,
        "proxy_err": 0.032984498888254166,
        "err": 211.4678955078125,
        "tr(WHW.T)": 6411.12939453125,
        "mse": 4.020806954940781e-06,
        "bpp_sum": 258048,
        "bpp_loss_sum": 157089072.0,
        "direction": "col",
        "num_pixels": 58720256
    },
    "6_q.pt": {
        "W_hat": null,
        "bpp_loss": 2.6380064487457275,
        "bpp": 0.0,
        "proxy_err": 0.0043491702526807785,
        "err": 155.00262451171875,
        "tr(WHW.T)": 35639.5859375,
        "mse": 1.1921873010578565e-05,
        "bpp_sum": 73728,
        "bpp_loss_sum": 44332132.0,
        "direction": "col",
        "num_pixels": 16777216
    },
    "6_k.pt": {
        "W_hat": null,
        "bpp_loss": 2.64998459815979,
        "bpp": 0.0,
        "proxy_err": 0.0037624924443662167,
        "err": 98.4405517578125,
        "tr(WHW.T)": 26163.654296875,
        "mse": 2.658710400282871e-05,
        "bpp_sum": 73728,
        "bpp_loss_sum": 11188569.0,
        "direction": "col",
        "num_pixels": 4194304
    },
    "6_v.pt": {
        "W_hat": null,
        "bpp_loss": 2.665642499923706,
        "bpp": 0.0,
        "proxy_err": 0.022514335811138153,
        "err": 5.710395812988281,
        "tr(WHW.T)": 253.63375854492188,
        "mse": 2.2638009795628022e-06,
        "bpp_sum": 73728,
        "bpp_loss_sum": 11254243.0,
        "direction": "col",
        "num_pixels": 4194304
    },
    "6_o.pt": {
        "W_hat": null,
        "bpp_loss": 2.669590473175049,
        "bpp": 0.0,
        "proxy_err": 0.038571301847696304,
        "err": 38.924163818359375,
        "tr(WHW.T)": 1009.1483154296875,
        "mse": 2.9892071324866265e-06,
        "bpp_sum": 73728,
        "bpp_loss_sum": 44862024.0,
        "direction": "col",
        "num_pixels": 16777216
    },
    "6_up.pt": {
        "W_hat": null,
        "bpp_loss": 2.6702077048165456,
        "bpp": 0.0,
        "proxy_err": 0.026860065758228302,
        "err": 212.82667541503906,
        "tr(WHW.T)": 7923.53515625,
        "mse": 4.065235316375038e-06,
        "bpp_sum": 73728,
        "bpp_loss_sum": 156869008.0,
        "direction": "col",
        "num_pixels": 58720256
    },
    "6_gate.pt": {
        "W_hat": null,
        "bpp_loss": 2.6726205008370534,
        "bpp": 0.0,
        "proxy_err": 0.010714839212596416,
        "err": 383.03826904296875,
        "tr(WHW.T)": 35748.390625,
        "mse": 7.1220547397388145e-06,
        "bpp_sum": 73728,
        "bpp_loss_sum": 157010688.0,
        "direction": "col",
        "num_pixels": 58720256
    },
    "6_down.pt": {
        "W_hat": null,
        "bpp_loss": 2.671123777117048,
        "bpp": 0.0,
        "proxy_err": 0.03276493400335312,
        "err": 212.4333953857422,
        "tr(WHW.T)": 6483.5595703125,
        "mse": 4.0112440728989895e-06,
        "bpp_sum": 258048,
        "bpp_loss_sum": 157107120.0,
        "direction": "col",
        "num_pixels": 58720256
    },
    "7_q.pt": {
        "W_hat": null,
        "bpp_loss": 2.6404974460601807,
        "bpp": 0.0,
        "proxy_err": 0.00414044177159667,
        "err": 145.515625,
        "tr(WHW.T)": 35144.953125,
        "mse": 1.1010642992914654e-05,
        "bpp_sum": 73728,
        "bpp_loss_sum": 44373924.0,
        "direction": "col",
        "num_pixels": 16777216
    },
    "7_k.pt": {
        "W_hat": null,
        "bpp_loss": 2.6536450386047363,
        "bpp": 0.0,
        "proxy_err": 0.0036916921380907297,
        "err": 99.12374877929688,
        "tr(WHW.T)": 26850.4921875,
        "mse": 2.7348543881089427e-05,
        "bpp_sum": 73728,
        "bpp_loss_sum": 11203922.0,
        "direction": "col",
        "num_pixels": 4194304
    },
    "7_v.pt": {
        "W_hat": null,
        "bpp_loss": 2.6636862754821777,
        "bpp": 0.0,
        "proxy_err": 0.019792141392827034,
        "err": 6.124224662780762,
        "tr(WHW.T)": 309.4270935058594,
        "mse": 2.2158708361530444e-06,
        "bpp_sum": 73728,
        "bpp_loss_sum": 11246038.0,
        "direction": "col",
        "num_pixels": 4194304
    },
    "7_o.pt": {
        "W_hat": null,
        "bpp_loss": 2.667125940322876,
        "bpp": 0.0,
        "proxy_err": 0.03926054760813713,
        "err": 37.65932846069336,
        "tr(WHW.T)": 959.215576171875,
        "mse": 3.0937421797716524e-06,
        "bpp_sum": 73728,
        "bpp_loss_sum": 44820676.0,
        "direction": "col",
        "num_pixels": 16777216
    },
    "7_up.pt": {
        "W_hat": null,
        "bpp_loss": 2.6683357783726285,
        "bpp": 0.0,
        "proxy_err": 0.02503153868019581,
        "err": 215.9583282470703,
        "tr(WHW.T)": 8627.44921875,
        "mse": 4.176923539489508e-06,
        "bpp_sum": 73728,
        "bpp_loss_sum": 156759088.0,
        "direction": "col",
        "num_pixels": 58720256
    },
    "7_gate.pt": {
        "W_hat": null,
        "bpp_loss": 2.670392172677176,
        "bpp": 0.0,
        "proxy_err": 0.010437940247356892,
        "err": 364.32098388671875,
        "tr(WHW.T)": 34903.53125,
        "mse": 6.868674972793087e-06,
        "bpp_sum": 73728,
        "bpp_loss_sum": 156879840.0,
        "direction": "col",
        "num_pixels": 58720256
    },
    "7_down.pt": {
        "W_hat": null,
        "bpp_loss": 2.669337681361607,
        "bpp": 0.0,
        "proxy_err": 0.033821627497673035,
        "err": 221.01174926757812,
        "tr(WHW.T)": 6534.6279296875,
        "mse": 4.1176094782713335e-06,
        "bpp_sum": 258048,
        "bpp_loss_sum": 157002240.0,
        "direction": "col",
        "num_pixels": 58720256
    },
    "8_q.pt": {
        "W_hat": null,
        "bpp_loss": 2.6271467208862305,
        "bpp": 0.0,
        "proxy_err": 0.005134992301464081,
        "err": 136.59579467773438,
        "tr(WHW.T)": 26600.974609375,
        "mse": 1.1052050467696972e-05,
        "bpp_sum": 73728,
        "bpp_loss_sum": 44149936.0,
        "direction": "col",
        "num_pixels": 16777216
    },
    "8_k.pt": {
        "W_hat": null,
        "bpp_loss": 2.6336889266967773,
        "bpp": 0.0,
        "proxy_err": 0.004095687996596098,
        "err": 92.2707290649414,
        "tr(WHW.T)": 22528.75,
        "mse": 2.6613202862790786e-05,
        "bpp_sum": 73728,
        "bpp_loss_sum": 11120220.0,
        "direction": "col",
        "num_pixels": 4194304
    },
    "8_v.pt": {
        "W_hat": null,
        "bpp_loss": 2.6520915031433105,
        "bpp": 0.0,
        "proxy_err": 0.02393326163291931,
        "err": 6.167726516723633,
        "tr(WHW.T)": 257.7052307128906,
        "mse": 2.456507672832231e-06,
        "bpp_sum": 73728,
        "bpp_loss_sum": 11197406.0,
        "direction": "col",
        "num_pixels": 4194304
    },
    "8_o.pt": {
        "W_hat": null,
        "bpp_loss": 2.6666173934936523,
        "bpp": 0.0,
        "proxy_err": 0.05362449586391449,
        "err": 39.982757568359375,
        "tr(WHW.T)": 745.606201171875,
        "mse": 3.221909992134897e-06,
        "bpp_sum": 73728,
        "bpp_loss_sum": 44812144.0,
        "direction": "col",
        "num_pixels": 16777216
    },
    "8_up.pt": {
        "W_hat": null,
        "bpp_loss": 2.6688744681222096,
        "bpp": 0.0,
        "proxy_err": 0.025128372013568878,
        "err": 213.46688842773438,
        "tr(WHW.T)": 8495.0546875,
        "mse": 4.141973022342427e-06,
        "bpp_sum": 73728,
        "bpp_loss_sum": 156790720.0,
        "direction": "col",
        "num_pixels": 58720256
    },
    "8_gate.pt": {
        "W_hat": null,
        "bpp_loss": 2.668633052280971,
        "bpp": 0.0,
        "proxy_err": 0.009851714596152306,
        "err": 366.859619140625,
        "tr(WHW.T)": 37238.1484375,
        "mse": 6.933619260962587e-06,
        "bpp_sum": 73728,
        "bpp_loss_sum": 156776544.0,
        "direction": "col",
        "num_pixels": 58720256
    },
    "8_down.pt": {
        "W_hat": null,
        "bpp_loss": 2.669431413922991,
        "bpp": 0.0,
        "proxy_err": 0.03441451117396355,
        "err": 223.3094482421875,
        "tr(WHW.T)": 6488.81640625,
        "mse": 4.08049299949198e-06,
        "bpp_sum": 258048,
        "bpp_loss_sum": 157007744.0,
        "direction": "col",
        "num_pixels": 58720256
    },
    "9_q.pt": {
        "W_hat": null,
        "bpp_loss": 2.6350672245025635,
        "bpp": 0.0,
        "proxy_err": 0.005230586510151625,
        "err": 134.18145751953125,
        "tr(WHW.T)": 25653.234375,
        "mse": 1.1048823580495082e-05,
        "bpp_sum": 73728,
        "bpp_loss_sum": 44282820.0,
        "direction": "col",
        "num_pixels": 16777216
    },
    "9_k.pt": {
        "W_hat": null,
        "bpp_loss": 2.6419639587402344,
        "bpp": 0.0,
        "proxy_err": 0.004251659382134676,
        "err": 89.04096984863281,
        "tr(WHW.T)": 20942.638671875,
        "mse": 2.6667010388337076e-05,
        "bpp_sum": 73728,
        "bpp_loss_sum": 11154928.0,
        "direction": "col",
        "num_pixels": 4194304
    },
    "9_v.pt": {
        "W_hat": null,
        "bpp_loss": 2.6406707763671875,
        "bpp": 0.0,
        "proxy_err": 0.02429189346730709,
        "err": 8.536870956420898,
        "tr(WHW.T)": 351.4288024902344,
        "mse": 3.294226644356968e-06,
        "bpp_sum": 73728,
        "bpp_loss_sum": 11149504.0,
        "direction": "col",
        "num_pixels": 4194304
    },
    "9_o.pt": {
        "W_hat": null,
        "bpp_loss": 2.6670148372650146,
        "bpp": 0.0,
        "proxy_err": 0.05570264160633087,
        "err": 43.25876998901367,
        "tr(WHW.T)": 776.6017456054688,
        "mse": 3.701461309901788e-06,
        "bpp_sum": 73728,
        "bpp_loss_sum": 44818812.0,
        "direction": "col",
        "num_pixels": 16777216
    },
    "9_up.pt": {
        "W_hat": null,
        "bpp_loss": 2.667788641793387,
        "bpp": 0.0,
        "proxy_err": 0.0243291687220335,
        "err": 218.24832153320312,
        "tr(WHW.T)": 8970.64453125,
        "mse": 4.212658495816868e-06,
        "bpp_sum": 73728,
        "bpp_loss_sum": 156726960.0,
        "direction": "col",
        "num_pixels": 58720256
    },
    "9_gate.pt": {
        "W_hat": null,
        "bpp_loss": 2.6659039088657925,
        "bpp": 0.0,
        "proxy_err": 0.00958582479506731,
        "err": 377.8321838378906,
        "tr(WHW.T)": 39415.71875,
        "mse": 7.096211447787937e-06,
        "bpp_sum": 73728,
        "bpp_loss_sum": 156616288.0,
        "direction": "col",
        "num_pixels": 58720256
    },
    "9_down.pt": {
        "W_hat": null,
        "bpp_loss": 2.668969290597098,
        "bpp": 0.0,
        "proxy_err": 0.03517976775765419,
        "err": 220.67929077148438,
        "tr(WHW.T)": 6272.90380859375,
        "mse": 4.110311238036957e-06,
        "bpp_sum": 258048,
        "bpp_loss_sum": 156980608.0,
        "direction": "col",
        "num_pixels": 58720256
    },
    "10_q.pt": {
        "W_hat": null,
        "bpp_loss": 2.621150016784668,
        "bpp": 0.0,
        "proxy_err": 0.005736044142395258,
        "err": 133.8686981201172,
        "tr(WHW.T)": 23338.15625,
        "mse": 1.1491840268718079e-05,
        "bpp_sum": 73728,
        "bpp_loss_sum": 44049328.0,
        "direction": "col",
        "num_pixels": 16777216
    },
    "10_k.pt": {
        "W_hat": null,
        "bpp_loss": 2.633107900619507,
        "bpp": 0.0,
        "proxy_err": 0.004552876576781273,
        "err": 89.89179992675781,
        "tr(WHW.T)": 19743.95703125,
        "mse": 2.714595575525891e-05,
        "bpp_sum": 73728,
        "bpp_loss_sum": 11117783.0,
        "direction": "col",
        "num_pixels": 4194304
    },
    "10_v.pt": {
        "W_hat": null,
        "bpp_loss": 2.6492934226989746,
        "bpp": 0.0,
        "proxy_err": 0.022525398060679436,
        "err": 5.672771453857422,
        "tr(WHW.T)": 251.83889770507812,
        "mse": 2.395553110545734e-06,
        "bpp_sum": 73728,
        "bpp_loss_sum": 11185670.0,
        "direction": "col",
        "num_pixels": 4194304
    },
    "10_o.pt": {
        "W_hat": null,
        "bpp_loss": 2.667623519897461,
        "bpp": 0.0,
        "proxy_err": 0.05531423166394234,
        "err": 37.65040969848633,
        "tr(WHW.T)": 680.6640625,
        "mse": 3.1406659672938986e-06,
        "bpp_sum": 73728,
        "bpp_loss_sum": 44829024.0,
        "direction": "col",
        "num_pixels": 16777216
    },
    "10_up.pt": {
        "W_hat": null,
        "bpp_loss": 2.6699275970458984,
        "bpp": 0.0,
        "proxy_err": 0.024697795510292053,
        "err": 227.19888305664062,
        "tr(WHW.T)": 9199.15625,
        "mse": 4.350929430074757e-06,
        "bpp_sum": 73728,
        "bpp_loss_sum": 156852560.0,
        "direction": "col",
        "num_pixels": 58720256
    },
    "10_gate.pt": {
        "W_hat": null,
        "bpp_loss": 2.6680725642613004,
        "bpp": 0.0,
        "proxy_err": 0.009703329764306545,
        "err": 362.8984069824219,
        "tr(WHW.T)": 37399.3671875,
        "mse": 6.753065918019274e-06,
        "bpp_sum": 73728,
        "bpp_loss_sum": 156743632.0,
        "direction": "col",
        "num_pixels": 58720256
    },
    "10_down.pt": {
        "W_hat": null,
        "bpp_loss": 2.670119149344308,
        "bpp": 0.0,
        "proxy_err": 0.034941427409648895,
        "err": 228.0009765625,
        "tr(WHW.T)": 6525.2333984375,
        "mse": 4.2259171095793135e-06,
        "bpp_sum": 258048,
        "bpp_loss_sum": 157048128.0,
        "direction": "col",
        "num_pixels": 58720256
    },
    "11_q.pt": {
        "W_hat": null,
        "bpp_loss": 2.637213945388794,
        "bpp": 0.0,
        "proxy_err": 0.005503950174897909,
        "err": 122.1375961303711,
        "tr(WHW.T)": 22190.8984375,
        "mse": 1.0362151442677714e-05,
        "bpp_sum": 73728,
        "bpp_loss_sum": 44318836.0,
        "direction": "col",
        "num_pixels": 16777216
    },
    "11_k.pt": {
        "W_hat": null,
        "bpp_loss": 2.6441242694854736,
        "bpp": 0.0,
        "proxy_err": 0.004775614943355322,
        "err": 86.092041015625,
        "tr(WHW.T)": 18027.42578125,
        "mse": 2.670706089702435e-05,
        "bpp_sum": 73728,
        "bpp_loss_sum": 11163989.0,
        "direction": "col",
        "num_pixels": 4194304
    },
    "11_v.pt": {
        "W_hat": null,
        "bpp_loss": 2.663848400115967,
        "bpp": 0.0,
        "proxy_err": 0.01920558325946331,
        "err": 6.13751220703125,
        "tr(WHW.T)": 319.56915283203125,
        "mse": 2.3209167920867912e-06,
        "bpp_sum": 73728,
        "bpp_loss_sum": 11246718.0,
        "direction": "col",
        "num_pixels": 4194304
    },
    "11_o.pt": {
        "W_hat": null,
        "bpp_loss": 2.6670634746551514,
        "bpp": 0.0,
        "proxy_err": 0.06432536989450455,
        "err": 36.404788970947266,
        "tr(WHW.T)": 565.9476318359375,
        "mse": 3.277135874668602e-06,
        "bpp_sum": 73728,
        "bpp_loss_sum": 44819628.0,
        "direction": "col",
        "num_pixels": 16777216
    },
    "11_up.pt": {
        "W_hat": null,
        "bpp_loss": 2.668581553867885,
        "bpp": 0.0,
        "proxy_err": 0.024566948413848877,
        "err": 225.83399963378906,
        "tr(WHW.T)": 9192.5947265625,
        "mse": 4.416096544446191e-06,
        "bpp_sum": 73728,
        "bpp_loss_sum": 156773520.0,
        "direction": "col",
        "num_pixels": 58720256
    },
    "11_gate.pt": {
        "W_hat": null,
        "bpp_loss": 2.664087568010603,
        "bpp": 0.0,
        "proxy_err": 0.009428665973246098,
        "err": 347.7677917480469,
        "tr(WHW.T)": 36884.09375,
        "mse": 6.5840963543450925e-06,
        "bpp_sum": 73728,
        "bpp_loss_sum": 156509632.0,
        "direction": "col",
        "num_pixels": 58720256
    },
    "11_down.pt": {
        "W_hat": null,
        "bpp_loss": 2.6689976283482144,
        "bpp": 0.0,
        "proxy_err": 0.034154750406742096,
        "err": 227.3302764892578,
        "tr(WHW.T)": 6655.890625,
        "mse": 4.289937351131812e-06,
        "bpp_sum": 258048,
        "bpp_loss_sum": 156982272.0,
        "direction": "col",
        "num_pixels": 58720256
    },
    "12_q.pt": {
        "W_hat": null,
        "bpp_loss": 2.6508448123931885,
        "bpp": 0.0,
        "proxy_err": 0.00402104714885354,
        "err": 137.12826538085938,
        "tr(WHW.T)": 34102.625,
        "mse": 1.0602445399854332e-05,
        "bpp_sum": 73728,
        "bpp_loss_sum": 44547524.0,
        "direction": "col",
        "num_pixels": 16777216
    },
    "12_k.pt": {
        "W_hat": null,
        "bpp_loss": 2.6577792167663574,
        "bpp": 0.0,
        "proxy_err": 0.003782431362196803,
        "err": 87.211669921875,
        "tr(WHW.T)": 23057.0390625,
        "mse": 2.5523502699797973e-05,
        "bpp_sum": 73728,
        "bpp_loss_sum": 11221262.0,
        "direction": "col",
        "num_pixels": 4194304
    },
    "12_v.pt": {
        "W_hat": null,
        "bpp_loss": 2.6620850563049316,
        "bpp": 0.0,
        "proxy_err": 0.02466573193669319,
        "err": 8.969037055969238,
        "tr(WHW.T)": 363.6233825683594,
        "mse": 3.226195531169651e-06,
        "bpp_sum": 73728,
        "bpp_loss_sum": 11239322.0,
        "direction": "col",
        "num_pixels": 4194304
    },
    "12_o.pt": {
        "W_hat": null,
        "bpp_loss": 2.665158748626709,
        "bpp": 0.0,
        "proxy_err": 0.05632185563445091,
        "err": 43.91816711425781,
        "tr(WHW.T)": 779.7713012695312,
        "mse": 3.6782971619686577e-06,
        "bpp_sum": 73728,
        "bpp_loss_sum": 44787672.0,
        "direction": "col",
        "num_pixels": 16777216
    },
    "12_up.pt": {
        "W_hat": null,
        "bpp_loss": 2.6656011853899275,
        "bpp": 0.0,
        "proxy_err": 0.02283881977200508,
        "err": 229.00839233398438,
        "tr(WHW.T)": 10027.1552734375,
        "mse": 4.594936854118714e-06,
        "bpp_sum": 73728,
        "bpp_loss_sum": 156598512.0,
        "direction": "col",
        "num_pixels": 58720256
    },
    "12_gate.pt": {
        "W_hat": null,
        "bpp_loss": 2.6588706970214844,
        "bpp": 0.0,
        "proxy_err": 0.008937167935073376,
        "err": 333.6611633300781,
        "tr(WHW.T)": 37334.10546875,
        "mse": 6.4189175645879e-06,
        "bpp_sum": 73728,
        "bpp_loss_sum": 156203296.0,
        "direction": "col",
        "num_pixels": 58720256
    },
    "12_down.pt": {
        "W_hat": null,
        "bpp_loss": 2.668104716709682,
        "bpp": 0.0,
        "proxy_err": 0.033797379583120346,
        "err": 230.58978271484375,
        "tr(WHW.T)": 6822.7119140625,
        "mse": 4.432544301380403e-06,
        "bpp_sum": 258048,
        "bpp_loss_sum": 156929840.0,
        "direction": "col",
        "num_pixels": 58720256
    },
    "13_q.pt": {
        "W_hat": null,
        "bpp_loss": 2.636457681655884,
        "bpp": 0.0,
        "proxy_err": 0.006045267917215824,
        "err": 126.33023071289062,
        "tr(WHW.T)": 20897.375,
        "mse": 1.0874773579416797e-05,
        "bpp_sum": 73728,
        "bpp_loss_sum": 44306148.0,
        "direction": "col",
        "num_pixels": 16777216
    },
    "13_k.pt": {
        "W_hat": null,
        "bpp_loss": 2.6401050090789795,
        "bpp": 0.0,
        "proxy_err": 0.0051506757736206055,
        "err": 91.67643737792969,
        "tr(WHW.T)": 17798.9140625,
        "mse": 2.7026457246392965e-05,
        "bpp_sum": 73728,
        "bpp_loss_sum": 11147131.0,
        "direction": "col",
        "num_pixels": 4194304
    },
    "13_v.pt": {
        "W_hat": null,
        "bpp_loss": 2.662472724914551,
        "bpp": 0.0,
        "proxy_err": 0.02538769505918026,
        "err": 7.112453460693359,
        "tr(WHW.T)": 280.153564453125,
        "mse": 2.7574023988563567e-06,
        "bpp_sum": 73728,
        "bpp_loss_sum": 11240948.0,
        "direction": "col",
        "num_pixels": 4194304
    },
    "13_o.pt": {
        "W_hat": null,
        "bpp_loss": 2.668564796447754,
        "bpp": 0.0,
        "proxy_err": 0.06146816536784172,
        "err": 41.50372314453125,
        "tr(WHW.T)": 675.206787109375,
        "mse": 3.487275080260588e-06,
        "bpp_sum": 73728,
        "bpp_loss_sum": 44844816.0,
        "direction": "col",
        "num_pixels": 16777216
    },
    "13_up.pt": {
        "W_hat": null,
        "bpp_loss": 2.666499819074358,
        "bpp": 0.0,
        "proxy_err": 0.02301226556301117,
        "err": 230.35940551757812,
        "tr(WHW.T)": 10010.2880859375,
        "mse": 4.623976110451622e-06,
        "bpp_sum": 73728,
        "bpp_loss_sum": 156651280.0,
        "direction": "col",
        "num_pixels": 58720256
    },
    "13_gate.pt": {
        "W_hat": null,
        "bpp_loss": 2.6596295492989674,
        "bpp": 0.0,
        "proxy_err": 0.008666928857564926,
        "err": 337.32781982421875,
        "tr(WHW.T)": 38921.26171875,
        "mse": 6.431963356590131e-06,
        "bpp_sum": 73728,
        "bpp_loss_sum": 156247856.0,
        "direction": "col",
        "num_pixels": 58720256
    },
    "13_down.pt": {
        "W_hat": null,
        "bpp_loss": 2.670496804373605,
        "bpp": 0.0,
        "proxy_err": 0.035072844475507736,
        "err": 230.09561157226562,
        "tr(WHW.T)": 6560.505859375,
        "mse": 4.436638391780434e-06,
        "bpp_sum": 258048,
        "bpp_loss_sum": 157070304.0,
        "direction": "col",
        "num_pixels": 58720256
    },
    "14_q.pt": {
        "W_hat": null,
        "bpp_loss": 2.6344292163848877,
        "bpp": 0.0,
        "proxy_err": 0.005712417885661125,
        "err": 119.28577423095703,
        "tr(WHW.T)": 20881.8359375,
        "mse": 1.0417232260806486e-05,
        "bpp_sum": 73728,
        "bpp_loss_sum": 44272116.0,
        "direction": "col",
        "num_pixels": 16777216
    },
    "14_k.pt": {
        "W_hat": null,
        "bpp_loss": 2.629117965698242,
        "bpp": 0.0,
        "proxy_err": 0.004842607770115137,
        "err": 90.16596984863281,
        "tr(WHW.T)": 18619.30078125,
        "mse": 2.6501476895646192e-05,
        "bpp_sum": 73728,
        "bpp_loss_sum": 11101048.0,
        "direction": "col",
        "num_pixels": 4194304
    },
    "14_v.pt": {
        "W_hat": null,
        "bpp_loss": 2.6545684337615967,
        "bpp": 0.0,
        "proxy_err": 0.024068420752882957,
        "err": 6.77136754989624,
        "tr(WHW.T)": 281.3382568359375,
        "mse": 2.6873774459090782e-06,
        "bpp_sum": 73728,
        "bpp_loss_sum": 11207795.0,
        "direction": "col",
        "num_pixels": 4194304
    },
    "14_o.pt": {
        "W_hat": null,
        "bpp_loss": 2.6671924591064453,
        "bpp": 0.0,
        "proxy_err": 0.06279142200946808,
        "err": 43.09361267089844,
        "tr(WHW.T)": 686.2977294921875,
        "mse": 3.476271558611188e-06,
        "bpp_sum": 73728,
        "bpp_loss_sum": 44821792.0,
        "direction": "col",
        "num_pixels": 16777216
    },
    "14_up.pt": {
        "W_hat": null,
        "bpp_loss": 2.666484832763672,
        "bpp": 0.0,
        "proxy_err": 0.024594996124505997,
        "err": 225.39559936523438,
        "tr(WHW.T)": 9164.287109375,
        "mse": 4.5958527152833994e-06,
        "bpp_sum": 73728,
        "bpp_loss_sum": 156650400.0,
        "direction": "col",
        "num_pixels": 58720256
    },
    "14_gate.pt": {
        "W_hat": null,
        "bpp_loss": 2.656290054321289,
        "bpp": 0.0,
        "proxy_err": 0.00848754309117794,
        "err": 354.658935546875,
        "tr(WHW.T)": 41785.8203125,
        "mse": 6.738811407558387e-06,
        "bpp_sum": 73728,
        "bpp_loss_sum": 156051760.0,
        "direction": "col",
        "num_pixels": 58720256
    },
    "14_down.pt": {
        "W_hat": null,
        "bpp_loss": 2.6713357652936662,
        "bpp": 0.0,
        "proxy_err": 0.03560324013233185,
        "err": 227.5373077392578,
        "tr(WHW.T)": 6390.916015625,
        "mse": 4.428247393661877e-06,
        "bpp_sum": 258048,
        "bpp_loss_sum": 157119568.0,
        "direction": "col",
        "num_pixels": 58720256
    },
    "15_q.pt": {
        "W_hat": null,
        "bpp_loss": 2.6190388202667236,
        "bpp": 0.0,
        "proxy_err": 0.005556056741625071,
        "err": 156.0102081298828,
        "tr(WHW.T)": 28079.3046875,
        "mse": 1.2601840353454463e-05,
        "bpp_sum": 73728,
        "bpp_loss_sum": 44013908.0,
        "direction": "col",
        "num_pixels": 16777216
    },
    "15_k.pt": {
        "W_hat": null,
        "bpp_loss": 2.649799346923828,
        "bpp": 0.0,
        "proxy_err": 0.004742149729281664,
        "err": 89.49227905273438,
        "tr(WHW.T)": 18871.66796875,
        "mse": 2.5737004762049764e-05,
        "bpp_sum": 73728,
        "bpp_loss_sum": 11187792.0,
        "direction": "col",
        "num_pixels": 4194304
    },
    "15_v.pt": {
        "W_hat": null,
        "bpp_loss": 2.653751850128174,
        "bpp": 0.0,
        "proxy_err": 0.030245836824178696,
        "err": 8.590638160705566,
        "tr(WHW.T)": 284.0271301269531,
        "mse": 3.1484614737564698e-06,
        "bpp_sum": 73728,
        "bpp_loss_sum": 11204370.0,
        "direction": "col",
        "num_pixels": 4194304
    },
    "15_o.pt": {
        "W_hat": null,
        "bpp_loss": 2.668769359588623,
        "bpp": 0.0,
        "proxy_err": 0.05810695141553879,
        "err": 48.108367919921875,
        "tr(WHW.T)": 827.9279174804688,
        "mse": 3.72913814317144e-06,
        "bpp_sum": 73728,
        "bpp_loss_sum": 44848248.0,
        "direction": "col",
        "num_pixels": 16777216
    },
    "15_up.pt": {
        "W_hat": null,
        "bpp_loss": 2.6682521275111606,
        "bpp": 0.0,
        "proxy_err": 0.024893905967473984,
        "err": 223.9099884033203,
        "tr(WHW.T)": 8994.5703125,
        "mse": 4.521055416262243e-06,
        "bpp_sum": 73728,
        "bpp_loss_sum": 156754176.0,
        "direction": "col",
        "num_pixels": 58720256
    },
    "15_gate.pt": {
        "W_hat": null,
        "bpp_loss": 2.6603524344308034,
        "bpp": 0.0,
        "proxy_err": 0.00813749898225069,
        "err": 376.0986633300781,
        "tr(WHW.T)": 46217.96875,
        "mse": 7.078501766955014e-06,
        "bpp_sum": 73728,
        "bpp_loss_sum": 156290304.0,
        "direction": "col",
        "num_pixels": 58720256
    },
    "15_down.pt": {
        "W_hat": null,
        "bpp_loss": 2.670779364449637,
        "bpp": 0.0,
        "proxy_err": 0.035609714686870575,
        "err": 227.88034057617188,
        "tr(WHW.T)": 6399.38671875,
        "mse": 4.388463366922224e-06,
        "bpp_sum": 258048,
        "bpp_loss_sum": 157086896.0,
        "direction": "col",
        "num_pixels": 58720256
    },
    "16_q.pt": {
        "W_hat": null,
        "bpp_loss": 2.634598731994629,
        "bpp": 0.0,
        "proxy_err": 0.005491454154253006,
        "err": 134.46726989746094,
        "tr(WHW.T)": 24486.642578125,
        "mse": 1.1782995898101944e-05,
        "bpp_sum": 73728,
        "bpp_loss_sum": 44274960.0,
        "direction": "col",
        "num_pixels": 16777216
    },
    "16_k.pt": {
        "W_hat": null,
        "bpp_loss": 2.6420681476593018,
        "bpp": 0.0,
        "proxy_err": 0.0045166597701609135,
        "err": 88.10356903076172,
        "tr(WHW.T)": 19506.35546875,
        "mse": 2.611779564176686e-05,
        "bpp_sum": 73728,
        "bpp_loss_sum": 11155365.0,
        "direction": "col",
        "num_pixels": 4194304
    },
    "16_v.pt": {
        "W_hat": null,
        "bpp_loss": 2.656736135482788,
        "bpp": 0.0,
        "proxy_err": 0.026430413126945496,
        "err": 7.249378204345703,
        "tr(WHW.T)": 274.28167724609375,
        "mse": 2.751630290731555e-06,
        "bpp_sum": 73728,
        "bpp_loss_sum": 11216887.0,
        "direction": "col",
        "num_pixels": 4194304
    },
    "16_o.pt": {
        "W_hat": null,
        "bpp_loss": 2.6653833389282227,
        "bpp": 0.0,
        "proxy_err": 0.0460694320499897,
        "err": 44.645355224609375,
        "tr(WHW.T)": 969.0885009765625,
        "mse": 3.55126667272998e-06,
        "bpp_sum": 73728,
        "bpp_loss_sum": 44791440.0,
        "direction": "col",
        "num_pixels": 16777216
    },
    "16_up.pt": {
        "W_hat": null,
        "bpp_loss": 2.669658933367048,
        "bpp": 0.0,
        "proxy_err": 0.026977481320500374,
        "err": 224.7543182373047,
        "tr(WHW.T)": 8331.1826171875,
        "mse": 4.391855327412486e-06,
        "bpp_sum": 73728,
        "bpp_loss_sum": 156836784.0,
        "direction": "col",
        "num_pixels": 58720256
    },
    "16_gate.pt": {
        "W_hat": null,
        "bpp_loss": 2.6625077383858815,
        "bpp": 0.0,
        "proxy_err": 0.009746472351253033,
        "err": 401.322021484375,
        "tr(WHW.T)": 41176.1328125,
        "mse": 7.434959570673527e-06,
        "bpp_sum": 73728,
        "bpp_loss_sum": 156416864.0,
        "direction": "col",
        "num_pixels": 58720256
    },
    "16_down.pt": {
        "W_hat": null,
        "bpp_loss": 2.671095711844308,
        "bpp": 0.0,
        "proxy_err": 0.03474614396691322,
        "err": 218.49349975585938,
        "tr(WHW.T)": 6288.2802734375,
        "mse": 4.277715561329387e-06,
        "bpp_sum": 258048,
        "bpp_loss_sum": 157105472.0,
        "direction": "col",
        "num_pixels": 58720256
    },
    "17_q.pt": {
        "W_hat": null,
        "bpp_loss": 2.635951519012451,
        "bpp": 0.0,
        "proxy_err": 0.005371841602027416,
        "err": 148.1094207763672,
        "tr(WHW.T)": 27571.44140625,
        "mse": 1.2008640624117106e-05,
        "bpp_sum": 73728,
        "bpp_loss_sum": 44297656.0,
        "direction": "col",
        "num_pixels": 16777216
    },
    "17_k.pt": {
        "W_hat": null,
        "bpp_loss": 2.6464900970458984,
        "bpp": 0.0,
        "proxy_err": 0.005514095537364483,
        "err": 96.10966491699219,
        "tr(WHW.T)": 17429.814453125,
        "mse": 2.6150366466026753e-05,
        "bpp_sum": 73728,
        "bpp_loss_sum": 11173912.0,
        "direction": "col",
        "num_pixels": 4194304
    },
    "17_v.pt": {
        "W_hat": null,
        "bpp_loss": 2.656966209411621,
        "bpp": 0.0,
        "proxy_err": 0.03158067166805267,
        "err": 8.968058586120605,
        "tr(WHW.T)": 283.9730224609375,
        "mse": 3.3748115129128564e-06,
        "bpp_sum": 73728,
        "bpp_loss_sum": 11217852.0,
        "direction": "col",
        "num_pixels": 4194304
    },
    "17_o.pt": {
        "W_hat": null,
        "bpp_loss": 2.6694915294647217,
        "bpp": 0.0,
        "proxy_err": 0.04429437220096588,
        "err": 49.020545959472656,
        "tr(WHW.T)": 1106.69921875,
        "mse": 3.827107320830692e-06,
        "bpp_sum": 73728,
        "bpp_loss_sum": 44860364.0,
        "direction": "col",
        "num_pixels": 16777216
    },
    "17_up.pt": {
        "W_hat": null,
        "bpp_loss": 2.6699867248535156,
        "bpp": 0.0,
        "proxy_err": 0.026752762496471405,
        "err": 226.12884521484375,
        "tr(WHW.T)": 8452.5419921875,
        "mse": 4.349973551143194e-06,
        "bpp_sum": 73728,
        "bpp_loss_sum": 156856032.0,
        "direction": "col",
        "num_pixels": 58720256
    },
    "17_gate.pt": {
        "W_hat": null,
        "bpp_loss": 2.661642619541713,
        "bpp": 0.0,
        "proxy_err": 0.009940237738192081,
        "err": 414.6824951171875,
        "tr(WHW.T)": 41717.5625,
        "mse": 7.592880592710571e-06,
        "bpp_sum": 73728,
        "bpp_loss_sum": 156366064.0,
        "direction": "col",
        "num_pixels": 58720256
    },
    "17_down.pt": {
        "W_hat": null,
        "bpp_loss": 2.669518607003348,
        "bpp": 0.0,
        "proxy_err": 0.03510002791881561,
        "err": 218.05242919921875,
        "tr(WHW.T)": 6212.31494140625,
        "mse": 4.271240868547466e-06,
        "bpp_sum": 258048,
        "bpp_loss_sum": 157012864.0,
        "direction": "col",
        "num_pixels": 58720256
    },
    "18_q.pt": {
        "W_hat": null,
        "bpp_loss": 2.6478559970855713,
        "bpp": 0.0,
        "proxy_err": 0.006413180381059647,
        "err": 143.6520233154297,
        "tr(WHW.T)": 22399.498046875,
        "mse": 1.1667028047668282e-05,
        "bpp_sum": 73728,
        "bpp_loss_sum": 44497380.0,
        "direction": "col",
        "num_pixels": 16777216
    },
    "18_k.pt": {
        "W_hat": null,
        "bpp_loss": 2.651174545288086,
        "bpp": 0.0,
        "proxy_err": 0.005817662924528122,
        "err": 101.1971435546875,
        "tr(WHW.T)": 17394.810546875,
        "mse": 2.7402227715356275e-05,
        "bpp_sum": 73728,
        "bpp_loss_sum": 11193560.0,
        "direction": "col",
        "num_pixels": 4194304
    },
    "18_v.pt": {
        "W_hat": null,
        "bpp_loss": 2.65541410446167,
        "bpp": 0.0,
        "proxy_err": 0.027795983478426933,
        "err": 7.994507789611816,
        "tr(WHW.T)": 287.61376953125,
        "mse": 2.689145503609325e-06,
        "bpp_sum": 73728,
        "bpp_loss_sum": 11211342.0,
        "direction": "col",
        "num_pixels": 4194304
    },
    "18_o.pt": {
        "W_hat": null,
        "bpp_loss": 2.6703710556030273,
        "bpp": 0.0,
        "proxy_err": 0.03820221871137619,
        "err": 45.96466827392578,
        "tr(WHW.T)": 1203.1937255859375,
        "mse": 3.6140384054306196e-06,
        "bpp_sum": 73728,
        "bpp_loss_sum": 44875120.0,
        "direction": "col",
        "num_pixels": 16777216
    },
    "18_up.pt": {
        "W_hat": null,
        "bpp_loss": 2.6720902579171315,
        "bpp": 0.0,
        "proxy_err": 0.028742006048560143,
        "err": 229.444091796875,
        "tr(WHW.T)": 7982.8837890625,
        "mse": 4.299465217627585e-06,
        "bpp_sum": 73728,
        "bpp_loss_sum": 156979552.0,
        "direction": "col",
        "num_pixels": 58720256
    },
    "18_gate.pt": {
        "W_hat": null,
        "bpp_loss": 2.6656810215541293,
        "bpp": 0.0,
        "proxy_err": 0.01200005505234003,
        "err": 422.9245910644531,
        "tr(WHW.T)": 35243.5546875,
        "mse": 7.641775482625235e-06,
        "bpp_sum": 73728,
        "bpp_loss_sum": 156603200.0,
        "direction": "col",
        "num_pixels": 58720256
    },
    "18_down.pt": {
        "W_hat": null,
        "bpp_loss": 2.672344207763672,
        "bpp": 0.0,
        "proxy_err": 0.034464702010154724,
        "err": 214.59716796875,
        "tr(WHW.T)": 6226.57861328125,
        "mse": 4.245546278980328e-06,
        "bpp_sum": 258048,
        "bpp_loss_sum": 157178784.0,
        "direction": "col",
        "num_pixels": 58720256
    },
    "19_q.pt": {
        "W_hat": null,
        "bpp_loss": 2.6449429988861084,
        "bpp": 0.0,
        "proxy_err": 0.006250171922147274,
        "err": 150.24185180664062,
        "tr(WHW.T)": 24038.03515625,
        "mse": 1.164138302556239e-05,
        "bpp_sum": 73728,
        "bpp_loss_sum": 44448508.0,
        "direction": "col",
        "num_pixels": 16777216
    },
    "19_k.pt": {
        "W_hat": null,
        "bpp_loss": 2.651210308074951,
        "bpp": 0.0,
        "proxy_err": 0.006034138146787882,
        "err": 93.8506851196289,
        "tr(WHW.T)": 15553.287109375,
        "mse": 2.544849121477455e-05,
        "bpp_sum": 73728,
        "bpp_loss_sum": 11193710.0,
        "direction": "col",
        "num_pixels": 4194304
    },
    "19_v.pt": {
        "W_hat": null,
        "bpp_loss": 2.657963275909424,
        "bpp": 0.0,
        "proxy_err": 0.027119332924485207,
        "err": 9.249311447143555,
        "tr(WHW.T)": 341.0596923828125,
        "mse": 3.0257319849624764e-06,
        "bpp_sum": 73728,
        "bpp_loss_sum": 11222034.0,
        "direction": "col",
        "num_pixels": 4194304
    },
    "19_o.pt": {
        "W_hat": null,
        "bpp_loss": 2.6702864170074463,
        "bpp": 0.0,
        "proxy_err": 0.039865314960479736,
        "err": 46.59823989868164,
        "tr(WHW.T)": 1168.891845703125,
        "mse": 3.711159024533117e-06,
        "bpp_sum": 73728,
        "bpp_loss_sum": 44873700.0,
        "direction": "col",
        "num_pixels": 16777216
    },
    "19_up.pt": {
        "W_hat": null,
        "bpp_loss": 2.672792434692383,
        "bpp": 0.0,
        "proxy_err": 0.029954945668578148,
        "err": 229.13412475585938,
        "tr(WHW.T)": 7649.2919921875,
        "mse": 4.264744347892702e-06,
        "bpp_sum": 73728,
        "bpp_loss_sum": 157020784.0,
        "direction": "col",
        "num_pixels": 58720256
    },
    "19_gate.pt": {
        "W_hat": null,
        "bpp_loss": 2.6663780212402344,
        "bpp": 0.0,
        "proxy_err": 0.01307170744985342,
        "err": 428.90875244140625,
        "tr(WHW.T)": 32811.9921875,
        "mse": 7.7446120485547e-06,
        "bpp_sum": 73728,
        "bpp_loss_sum": 156644128.0,
        "direction": "col",
        "num_pixels": 58720256
    },
    "19_down.pt": {
        "W_hat": null,
        "bpp_loss": 2.672235761369978,
        "bpp": 0.0,
        "proxy_err": 0.034046877175569534,
        "err": 210.50283813476562,
        "tr(WHW.T)": 6182.73583984375,
        "mse": 4.224733402224956e-06,
        "bpp_sum": 258048,
        "bpp_loss_sum": 157172416.0,
        "direction": "col",
        "num_pixels": 58720256
    },
    "20_q.pt": {
        "W_hat": null,
        "bpp_loss": 2.6429173946380615,
        "bpp": 0.0,
        "proxy_err": 0.006722678896039724,
        "err": 139.41317749023438,
        "tr(WHW.T)": 20737.7421875,
        "mse": 1.1388166967662983e-05,
        "bpp_sum": 73728,
        "bpp_loss_sum": 44414524.0,
        "direction": "col",
        "num_pixels": 16777216
    },
    "20_k.pt": {
        "W_hat": null,
        "bpp_loss": 2.6487860679626465,
        "bpp": 0.0,
        "proxy_err": 0.0060408092103898525,
        "err": 93.0031509399414,
        "tr(WHW.T)": 15395.8095703125,
        "mse": 2.4538367142667994e-05,
        "bpp_sum": 73728,
        "bpp_loss_sum": 11183542.0,
        "direction": "col",
        "num_pixels": 4194304
    },
    "20_v.pt": {
        "W_hat": null,
        "bpp_loss": 2.6559736728668213,
        "bpp": 0.0,
        "proxy_err": 0.028458159416913986,
        "err": 9.396660804748535,
        "tr(WHW.T)": 330.192138671875,
        "mse": 3.365388693055138e-06,
        "bpp_sum": 73728,
        "bpp_loss_sum": 11213689.0,
        "direction": "col",
        "num_pixels": 4194304
    },
    "20_o.pt": {
        "W_hat": null,
        "bpp_loss": 2.6661734580993652,
        "bpp": 0.0,
        "proxy_err": 0.03924528509378433,
        "err": 47.29539489746094,
        "tr(WHW.T)": 1205.1229248046875,
        "mse": 3.6439519135456067e-06,
        "bpp_sum": 73728,
        "bpp_loss_sum": 44804696.0,
        "direction": "col",
        "num_pixels": 16777216
    },
    "20_up.pt": {
        "W_hat": null,
        "bpp_loss": 2.67321286882673,
        "bpp": 0.0,
        "proxy_err": 0.030502663925290108,
        "err": 231.809814453125,
        "tr(WHW.T)": 7599.658203125,
        "mse": 4.294092832424212e-06,
        "bpp_sum": 73728,
        "bpp_loss_sum": 157045472.0,
        "direction": "col",
        "num_pixels": 58720256
    },
    "20_gate.pt": {
        "W_hat": null,
        "bpp_loss": 2.668539592197963,
        "bpp": 0.0,
        "proxy_err": 0.014022828079760075,
        "err": 430.01025390625,
        "tr(WHW.T)": 30665.015625,
        "mse": 7.744664799247403e-06,
        "bpp_sum": 73728,
        "bpp_loss_sum": 156771056.0,
        "direction": "col",
        "num_pixels": 58720256
    },
    "20_down.pt": {
        "W_hat": null,
        "bpp_loss": 2.672982624598912,
        "bpp": 0.0,
        "proxy_err": 0.03349180519580841,
        "err": 211.02725219726562,
        "tr(WHW.T)": 6300.8623046875,
        "mse": 4.258630724507384e-06,
        "bpp_sum": 258048,
        "bpp_loss_sum": 157216272.0,
        "direction": "col",
        "num_pixels": 58720256
    },
    "21_q.pt": {
        "W_hat": null,
        "bpp_loss": 2.6485939025878906,
        "bpp": 0.0,
        "proxy_err": 0.0054679149761796,
        "err": 141.2805938720703,
        "tr(WHW.T)": 25838.111328125,
        "mse": 1.1108448234153911e-05,
        "bpp_sum": 73728,
        "bpp_loss_sum": 44509760.0,
        "direction": "col",
        "num_pixels": 16777216
    },
    "21_k.pt": {
        "W_hat": null,
        "bpp_loss": 2.653947591781616,
        "bpp": 0.0,
        "proxy_err": 0.005599651951342821,
        "err": 94.00389099121094,
        "tr(WHW.T)": 16787.453125,
        "mse": 2.5032526536961086e-05,
        "bpp_sum": 73728,
        "bpp_loss_sum": 11205191.0,
        "direction": "col",
        "num_pixels": 4194304
    },
    "21_v.pt": {
        "W_hat": null,
        "bpp_loss": 2.6526012420654297,
        "bpp": 0.0,
        "proxy_err": 0.02844775840640068,
        "err": 10.32292652130127,
        "tr(WHW.T)": 362.87310791015625,
        "mse": 3.5898438000003807e-06,
        "bpp_sum": 73728,
        "bpp_loss_sum": 11199544.0,
        "direction": "col",
        "num_pixels": 4194304
    },
    "21_o.pt": {
        "W_hat": null,
        "bpp_loss": 2.654029130935669,
        "bpp": 0.0,
        "proxy_err": 0.033751197159290314,
        "err": 42.7515869140625,
        "tr(WHW.T)": 1266.6688232421875,
        "mse": 3.824093255389016e-06,
        "bpp_sum": 73728,
        "bpp_loss_sum": 44600948.0,
        "direction": "col",
        "num_pixels": 16777216
    },
    "21_up.pt": {
        "W_hat": null,
        "bpp_loss": 2.672652108328683,
        "bpp": 0.0,
        "proxy_err": 0.029890943318605423,
        "err": 232.32948303222656,
        "tr(WHW.T)": 7772.5712890625,
        "mse": 4.319107574701775e-06,
        "bpp_sum": 73728,
        "bpp_loss_sum": 157012544.0,
        "direction": "col",
        "num_pixels": 58720256
    },
    "21_gate.pt": {
        "W_hat": null,
        "bpp_loss": 2.6672060830252513,
        "bpp": 0.0,
        "proxy_err": 0.013802614063024521,
        "err": 435.6986083984375,
        "tr(WHW.T)": 31566.3828125,
        "mse": 7.872724381741136e-06,
        "bpp_sum": 73728,
        "bpp_loss_sum": 156692752.0,
        "direction": "col",
        "num_pixels": 58720256
    },
    "21_down.pt": {
        "W_hat": null,
        "bpp_loss": 2.6718542916434154,
        "bpp": 0.0,
        "proxy_err": 0.032364726066589355,
        "err": 205.5634307861328,
        "tr(WHW.T)": 6351.46484375,
        "mse": 4.286892362870276e-06,
        "bpp_sum": 258048,
        "bpp_loss_sum": 157150016.0,
        "direction": "col",
        "num_pixels": 58720256
    },
    "22_q.pt": {
        "W_hat": null,
        "bpp_loss": 2.6519949436187744,
        "bpp": 0.0,
        "proxy_err": 0.00621948903426528,
        "err": 126.37757110595703,
        "tr(WHW.T)": 20319.607421875,
        "mse": 1.0557440873526502e-05,
        "bpp_sum": 73728,
        "bpp_loss_sum": 44566820.0,
        "direction": "col",
        "num_pixels": 16777216
    },
    "22_k.pt": {
        "W_hat": null,
        "bpp_loss": 2.6524155139923096,
        "bpp": 0.0,
        "proxy_err": 0.0059211645275354385,
        "err": 87.18380737304688,
        "tr(WHW.T)": 14724.09765625,
        "mse": 2.390721783740446e-05,
        "bpp_sum": 73728,
        "bpp_loss_sum": 11198765.0,
        "direction": "col",
        "num_pixels": 4194304
    },
    "22_v.pt": {
        "W_hat": null,
        "bpp_loss": 2.6638753414154053,
        "bpp": 0.0,
        "proxy_err": 0.03153156489133835,
        "err": 10.912410736083984,
        "tr(WHW.T)": 346.0789489746094,
        "mse": 3.970633770222776e-06,
        "bpp_sum": 73728,
        "bpp_loss_sum": 11246831.0,
        "direction": "col",
        "num_pixels": 4194304
    },
    "22_o.pt": {
        "W_hat": null,
        "bpp_loss": 2.6709461212158203,
        "bpp": 0.0,
        "proxy_err": 0.04411335662007332,
        "err": 53.89906311035156,
        "tr(WHW.T)": 1221.8309326171875,
        "mse": 3.928782007278642e-06,
        "bpp_sum": 73728,
        "bpp_loss_sum": 44884768.0,
        "direction": "col",
        "num_pixels": 16777216
    },
    "22_up.pt": {
        "W_hat": null,
        "bpp_loss": 2.6738068716866628,
        "bpp": 0.0,
        "proxy_err": 0.031181730329990387,
        "err": 235.33648681640625,
        "tr(WHW.T)": 7547.25537109375,
        "mse": 4.345423349150224e-06,
        "bpp_sum": 73728,
        "bpp_loss_sum": 157080352.0,
        "direction": "col",
        "num_pixels": 58720256
    },
    "22_gate.pt": {
        "W_hat": null,
        "bpp_loss": 2.671060562133789,
        "bpp": 0.0,
        "proxy_err": 0.014806052669882774,
        "err": 437.283447265625,
        "tr(WHW.T)": 29534.099609375,
        "mse": 7.876466952438932e-06,
        "bpp_sum": 73728,
        "bpp_loss_sum": 156919088.0,
        "direction": "col",
        "num_pixels": 58720256
    },
    "22_down.pt": {
        "W_hat": null,
        "bpp_loss": 2.673335484095982,
        "bpp": 0.0,
        "proxy_err": 0.03237737715244293,
        "err": 211.40780639648438,
        "tr(WHW.T)": 6529.4912109375,
        "mse": 4.3119193833263125e-06,
        "bpp_sum": 258048,
        "bpp_loss_sum": 157236992.0,
        "direction": "col",
        "num_pixels": 58720256
    },
    "23_q.pt": {
        "W_hat": null,
        "bpp_loss": 2.65203857421875,
        "bpp": 0.0,
        "proxy_err": 0.006092999596148729,
        "err": 137.7562255859375,
        "tr(WHW.T)": 22608.93359375,
        "mse": 1.0579407899058424e-05,
        "bpp_sum": 73728,
        "bpp_loss_sum": 44567552.0,
        "direction": "col",
        "num_pixels": 16777216
    },
    "23_k.pt": {
        "W_hat": null,
        "bpp_loss": 2.65453839302063,
        "bpp": 0.0,
        "proxy_err": 0.0060346173122525215,
        "err": 89.6591796875,
        "tr(WHW.T)": 14857.4755859375,
        "mse": 2.3726039216853678e-05,
        "bpp_sum": 73728,
        "bpp_loss_sum": 11207669.0,
        "direction": "col",
        "num_pixels": 4194304
    },
    "23_v.pt": {
        "W_hat": null,
        "bpp_loss": 2.6676220893859863,
        "bpp": 0.0,
        "proxy_err": 0.03223344311118126,
        "err": 12.825913429260254,
        "tr(WHW.T)": 397.90704345703125,
        "mse": 4.418287062435411e-06,
        "bpp_sum": 73728,
        "bpp_loss_sum": 11262546.0,
        "direction": "col",
        "num_pixels": 4194304
    },
    "23_o.pt": {
        "W_hat": null,
        "bpp_loss": 2.6728196144104004,
        "bpp": 0.0,
        "proxy_err": 0.03236014023423195,
        "err": 56.451324462890625,
        "tr(WHW.T)": 1744.470947265625,
        "mse": 4.076840014022309e-06,
        "bpp_sum": 73728,
        "bpp_loss_sum": 44916200.0,
        "direction": "col",
        "num_pixels": 16777216
    },
    "23_up.pt": {
        "W_hat": null,
        "bpp_loss": 2.6738313947405135,
        "bpp": 0.0,
        "proxy_err": 0.03198615089058876,
        "err": 237.31190490722656,
        "tr(WHW.T)": 7419.2080078125,
        "mse": 4.379774509288836e-06,
        "bpp_sum": 73728,
        "bpp_loss_sum": 157081792.0,
        "direction": "col",
        "num_pixels": 58720256
    },
    "23_gate.pt": {
        "W_hat": null,
        "bpp_loss": 2.6708458491734097,
        "bpp": 0.0,
        "proxy_err": 0.01602085307240486,
        "err": 437.23553466796875,
        "tr(WHW.T)": 27291.65234375,
        "mse": 7.913074114185292e-06,
        "bpp_sum": 73728,
        "bpp_loss_sum": 156906480.0,
        "direction": "col",
        "num_pixels": 58720256
    },
    "23_down.pt": {
        "W_hat": null,
        "bpp_loss": 2.673552921840123,
        "bpp": 0.0,
        "proxy_err": 0.03180386498570442,
        "err": 212.03590393066406,
        "tr(WHW.T)": 6666.9853515625,
        "mse": 4.3463332985993475e-06,
        "bpp_sum": 258048,
        "bpp_loss_sum": 157249760.0,
        "direction": "col",
        "num_pixels": 58720256
    },
    "24_q.pt": {
        "W_hat": null,
        "bpp_loss": 2.6486527919769287,
        "bpp": 0.0,
        "proxy_err": 0.005907529499381781,
        "err": 132.54193115234375,
        "tr(WHW.T)": 22436.1015625,
        "mse": 1.0201189070357941e-05,
        "bpp_sum": 73728,
        "bpp_loss_sum": 44510748.0,
        "direction": "col",
        "num_pixels": 16777216
    },
    "24_k.pt": {
        "W_hat": null,
        "bpp_loss": 2.6455204486846924,
        "bpp": 0.0,
        "proxy_err": 0.005723262205719948,
        "err": 81.17550659179688,
        "tr(WHW.T)": 14183.43359375,
        "mse": 2.1337807993404567e-05,
        "bpp_sum": 73728,
        "bpp_loss_sum": 11169845.0,
        "direction": "col",
        "num_pixels": 4194304
    },
    "24_v.pt": {
        "W_hat": null,
        "bpp_loss": 2.6596553325653076,
        "bpp": 0.0,
        "proxy_err": 0.032905079424381256,
        "err": 15.375831604003906,
        "tr(WHW.T)": 467.2783508300781,
        "mse": 5.303692887537181e-06,
        "bpp_sum": 73728,
        "bpp_loss_sum": 11229131.0,
        "direction": "col",
        "num_pixels": 4194304
    },
    "24_o.pt": {
        "W_hat": null,
        "bpp_loss": 2.672585964202881,
        "bpp": 0.0,
        "proxy_err": 0.03550789877772331,
        "err": 56.43952560424805,
        "tr(WHW.T)": 1589.4921875,
        "mse": 4.4818289097747765e-06,
        "bpp_sum": 73728,
        "bpp_loss_sum": 44912280.0,
        "direction": "col",
        "num_pixels": 16777216
    },
    "24_up.pt": {
        "W_hat": null,
        "bpp_loss": 2.6737145015171597,
        "bpp": 0.0,
        "proxy_err": 0.03284319117665291,
        "err": 240.12127685546875,
        "tr(WHW.T)": 7311.1435546875,
        "mse": 4.418792286742246e-06,
        "bpp_sum": 73728,
        "bpp_loss_sum": 157074928.0,
        "direction": "col",
        "num_pixels": 58720256
    },
    "24_gate.pt": {
        "W_hat": null,
        "bpp_loss": 2.669806889125279,
        "bpp": 0.0,
        "proxy_err": 0.017094526439905167,
        "err": 442.35955810546875,
        "tr(WHW.T)": 25877.26171875,
        "mse": 7.98800010670675e-06,
        "bpp_sum": 73728,
        "bpp_loss_sum": 156845472.0,
        "direction": "col",
        "num_pixels": 58720256
    },
    "24_down.pt": {
        "W_hat": null,
        "bpp_loss": 2.673978805541992,
        "bpp": 0.0,
        "proxy_err": 0.03124310076236725,
        "err": 210.63902282714844,
        "tr(WHW.T)": 6741.93701171875,
        "mse": 4.388901288621128e-06,
        "bpp_sum": 258048,
        "bpp_loss_sum": 157274768.0,
        "direction": "col",
        "num_pixels": 58720256
    },
    "25_q.pt": {
        "W_hat": null,
        "bpp_loss": 2.6499576568603516,
        "bpp": 0.0,
        "proxy_err": 0.005110799800604582,
        "err": 133.45335388183594,
        "tr(WHW.T)": 26112.029296875,
        "mse": 9.85507449513534e-06,
        "bpp_sum": 73728,
        "bpp_loss_sum": 44532640.0,
        "direction": "col",
        "num_pixels": 16777216
    },
    "25_k.pt": {
        "W_hat": null,
        "bpp_loss": 2.645047664642334,
        "bpp": 0.0,
        "proxy_err": 0.005598494783043861,
        "err": 80.71137237548828,
        "tr(WHW.T)": 14416.6201171875,
        "mse": 2.1296767954481766e-05,
        "bpp_sum": 73728,
        "bpp_loss_sum": 11167862.0,
        "direction": "col",
        "num_pixels": 4194304
    },
    "25_v.pt": {
        "W_hat": null,
        "bpp_loss": 2.662471055984497,
        "bpp": 0.0,
        "proxy_err": 0.02897207997739315,
        "err": 16.160877227783203,
        "tr(WHW.T)": 557.8086547851562,
        "mse": 5.363908712752163e-06,
        "bpp_sum": 73728,
        "bpp_loss_sum": 11240941.0,
        "direction": "col",
        "num_pixels": 4194304
    },
    "25_o.pt": {
        "W_hat": null,
        "bpp_loss": 2.665942430496216,
        "bpp": 0.0,
        "proxy_err": 0.028873611241579056,
        "err": 57.472381591796875,
        "tr(WHW.T)": 1990.481201171875,
        "mse": 4.558589807857061e-06,
        "bpp_sum": 73728,
        "bpp_loss_sum": 44800820.0,
        "direction": "col",
        "num_pixels": 16777216
    },
    "25_up.pt": {
        "W_hat": null,
        "bpp_loss": 2.6734605516706194,
        "bpp": 0.0,
        "proxy_err": 0.03295312076807022,
        "err": 243.2662353515625,
        "tr(WHW.T)": 7382.19091796875,
        "mse": 4.496333986026002e-06,
        "bpp_sum": 73728,
        "bpp_loss_sum": 157060016.0,
        "direction": "col",
        "num_pixels": 58720256
    },
    "25_gate.pt": {
        "W_hat": null,
        "bpp_loss": 2.6679109845842635,
        "bpp": 0.0,
        "proxy_err": 0.016964739188551903,
        "err": 446.298828125,
        "tr(WHW.T)": 26307.4375,
        "mse": 8.109505870379508e-06,
        "bpp_sum": 73728,
        "bpp_loss_sum": 156734144.0,
        "direction": "col",
        "num_pixels": 58720256
    },
    "25_down.pt": {
        "W_hat": null,
        "bpp_loss": 2.673998696463449,
        "bpp": 0.0,
        "proxy_err": 0.031241511926054955,
        "err": 206.69232177734375,
        "tr(WHW.T)": 6615.951171875,
        "mse": 4.465902748052031e-06,
        "bpp_sum": 258048,
        "bpp_loss_sum": 157275936.0,
        "direction": "col",
        "num_pixels": 58720256
    },
    "26_q.pt": {
        "W_hat": null,
        "bpp_loss": 2.6501758098602295,
        "bpp": 0.0,
        "proxy_err": 0.006090620066970587,
        "err": 130.3592529296875,
        "tr(WHW.T)": 21403.28125,
        "mse": 9.983410564018413e-06,
        "bpp_sum": 73728,
        "bpp_loss_sum": 44536300.0,
        "direction": "col",
        "num_pixels": 16777216
    },
    "26_k.pt": {
        "W_hat": null,
        "bpp_loss": 2.646176338195801,
        "bpp": 0.0,
        "proxy_err": 0.005691122263669968,
        "err": 87.78889465332031,
        "tr(WHW.T)": 15425.5859375,
        "mse": 2.244003007945139e-05,
        "bpp_sum": 73728,
        "bpp_loss_sum": 11172596.0,
        "direction": "col",
        "num_pixels": 4194304
    },
    "26_v.pt": {
        "W_hat": null,
        "bpp_loss": 2.658891439437866,
        "bpp": 0.0,
        "proxy_err": 0.03644145652651787,
        "err": 15.83548355102539,
        "tr(WHW.T)": 434.54583740234375,
        "mse": 6.039187610440422e-06,
        "bpp_sum": 73728,
        "bpp_loss_sum": 11225927.0,
        "direction": "col",
        "num_pixels": 4194304
    },
    "26_o.pt": {
        "W_hat": null,
        "bpp_loss": 2.6692636013031006,
        "bpp": 0.0,
        "proxy_err": 0.02496769279241562,
        "err": 59.64090347290039,
        "tr(WHW.T)": 2388.72314453125,
        "mse": 4.7640369302826e-06,
        "bpp_sum": 73728,
        "bpp_loss_sum": 44856540.0,
        "direction": "col",
        "num_pixels": 16777216
    },
    "26_up.pt": {
        "W_hat": null,
        "bpp_loss": 2.6734621865408763,
        "bpp": 0.0,
        "proxy_err": 0.03227495402097702,
        "err": 246.76318359375,
        "tr(WHW.T)": 7645.65576171875,
        "mse": 4.5683477765123826e-06,
        "bpp_sum": 73728,
        "bpp_loss_sum": 157060112.0,
        "direction": "col",
        "num_pixels": 58720256
    },
    "26_gate.pt": {
        "W_hat": null,
        "bpp_loss": 2.6639041900634766,
        "bpp": 0.0,
        "proxy_err": 0.01564043201506138,
        "err": 452.03106689453125,
        "tr(WHW.T)": 28901.4453125,
        "mse": 8.215674824896269e-06,
        "bpp_sum": 73728,
        "bpp_loss_sum": 156498864.0,
        "direction": "col",
        "num_pixels": 58720256
    },
    "26_down.pt": {
        "W_hat": null,
        "bpp_loss": 2.6738905225481306,
        "bpp": 0.0,
        "proxy_err": 0.03183755278587341,
        "err": 210.7271728515625,
        "tr(WHW.T)": 6618.82470703125,
        "mse": 4.54773453384405e-06,
        "bpp_sum": 258048,
        "bpp_loss_sum": 157269584.0,
        "direction": "col",
        "num_pixels": 58720256
    },
    "27_q.pt": {
        "W_hat": null,
        "bpp_loss": 2.6487112045288086,
        "bpp": 0.0,
        "proxy_err": 0.0061505576595664024,
        "err": 131.0435791015625,
        "tr(WHW.T)": 21305.966796875,
        "mse": 9.665383913670667e-06,
        "bpp_sum": 73728,
        "bpp_loss_sum": 44511728.0,
        "direction": "col",
        "num_pixels": 16777216
    },
    "27_k.pt": {
        "W_hat": null,
        "bpp_loss": 2.6430864334106445,
        "bpp": 0.0,
        "proxy_err": 0.006402168422937393,
        "err": 89.70475769042969,
        "tr(WHW.T)": 14011.62109375,
        "mse": 2.1791638573631644e-05,
        "bpp_sum": 73728,
        "bpp_loss_sum": 11159636.0,
        "direction": "col",
        "num_pixels": 4194304
    },
    "27_v.pt": {
        "W_hat": null,
        "bpp_loss": 2.654198169708252,
        "bpp": 0.0,
        "proxy_err": 0.03161068633198738,
        "err": 21.422367095947266,
        "tr(WHW.T)": 677.69384765625,
        "mse": 6.817017492721789e-06,
        "bpp_sum": 73728,
        "bpp_loss_sum": 11206242.0,
        "direction": "col",
        "num_pixels": 4194304
    },
    "27_o.pt": {
        "W_hat": null,
        "bpp_loss": 2.6684155464172363,
        "bpp": 0.0,
        "proxy_err": 0.0313250795006752,
        "err": 67.66078186035156,
        "tr(WHW.T)": 2159.95556640625,
        "mse": 4.933955096930731e-06,
        "bpp_sum": 73728,
        "bpp_loss_sum": 44842312.0,
        "direction": "col",
        "num_pixels": 16777216
    },
    "27_up.pt": {
        "W_hat": null,
        "bpp_loss": 2.673152106148856,
        "bpp": 0.0,
        "proxy_err": 0.030071748420596123,
        "err": 254.87594604492188,
        "tr(WHW.T)": 8475.5947265625,
        "mse": 4.679222456616117e-06,
        "bpp_sum": 73728,
        "bpp_loss_sum": 157041904.0,
        "direction": "col",
        "num_pixels": 58720256
    },
    "27_gate.pt": {
        "W_hat": null,
        "bpp_loss": 2.6622497013636996,
        "bpp": 0.0,
        "proxy_err": 0.014110999181866646,
        "err": 462.96832275390625,
        "tr(WHW.T)": 32809.0390625,
        "mse": 8.333233381563332e-06,
        "bpp_sum": 73728,
        "bpp_loss_sum": 156401712.0,
        "direction": "col",
        "num_pixels": 58720256
    },
    "27_down.pt": {
        "W_hat": null,
        "bpp_loss": 2.6740976061139787,
        "bpp": 0.0,
        "proxy_err": 0.027831722050905228,
        "err": 182.11289978027344,
        "tr(WHW.T)": 6543.357421875,
        "mse": 4.657553745346377e-06,
        "bpp_sum": 258048,
        "bpp_loss_sum": 157281744.0,
        "direction": "col",
        "num_pixels": 58720256
    },
    "28_q.pt": {
        "W_hat": null,
        "bpp_loss": 2.6528515815734863,
        "bpp": 0.0,
        "proxy_err": 0.005746086593717337,
        "err": 133.10171508789062,
        "tr(WHW.T)": 23163.888671875,
        "mse": 9.662278898758814e-06,
        "bpp_sum": 73728,
        "bpp_loss_sum": 44581192.0,
        "direction": "col",
        "num_pixels": 16777216
    },
    "28_k.pt": {
        "W_hat": null,
        "bpp_loss": 2.6577301025390625,
        "bpp": 0.0,
        "proxy_err": 0.0053413063287734985,
        "err": 80.08867645263672,
        "tr(WHW.T)": 14994.2119140625,
        "mse": 1.9866056391038e-05,
        "bpp_sum": 73728,
        "bpp_loss_sum": 11221056.0,
        "direction": "col",
        "num_pixels": 4194304
    },
    "28_v.pt": {
        "W_hat": null,
        "bpp_loss": 2.6582939624786377,
        "bpp": 0.0,
        "proxy_err": 0.03465443104505539,
        "err": 20.844100952148438,
        "tr(WHW.T)": 601.4844360351562,
        "mse": 7.518777238146868e-06,
        "bpp_sum": 73728,
        "bpp_loss_sum": 11223421.0,
        "direction": "col",
        "num_pixels": 4194304
    },
    "28_o.pt": {
        "W_hat": null,
        "bpp_loss": 2.6687777042388916,
        "bpp": 0.0,
        "proxy_err": 0.02780843712389469,
        "err": 69.83935546875,
        "tr(WHW.T)": 2511.44482421875,
        "mse": 5.1852148317266256e-06,
        "bpp_sum": 73728,
        "bpp_loss_sum": 44848388.0,
        "direction": "col",
        "num_pixels": 16777216
    },
    "28_up.pt": {
        "W_hat": null,
        "bpp_loss": 2.6722559247698103,
        "bpp": 0.0,
        "proxy_err": 0.025696462020277977,
        "err": 263.2877502441406,
        "tr(WHW.T)": 10246.0703125,
        "mse": 4.878663276031148e-06,
        "bpp_sum": 73728,
        "bpp_loss_sum": 156989280.0,
        "direction": "col",
        "num_pixels": 58720256
    },
    "28_gate.pt": {
        "W_hat": null,
        "bpp_loss": 2.6582518986293246,
        "bpp": 0.0,
        "proxy_err": 0.012666003778576851,
        "err": 454.97503662109375,
        "tr(WHW.T)": 35920.9609375,
        "mse": 8.239661838160828e-06,
        "bpp_sum": 73728,
        "bpp_loss_sum": 156166960.0,
        "direction": "col",
        "num_pixels": 58720256
    },
    "28_down.pt": {
        "W_hat": null,
        "bpp_loss": 2.6735621861049106,
        "bpp": 0.0,
        "proxy_err": 0.0278205294162035,
        "err": 200.5884552001953,
        "tr(WHW.T)": 7210.08740234375,
        "mse": 4.837713277083822e-06,
        "bpp_sum": 258048,
        "bpp_loss_sum": 157250304.0,
        "direction": "col",
        "num_pixels": 58720256
    },
    "29_q.pt": {
        "W_hat": null,
        "bpp_loss": 2.652010679244995,
        "bpp": 0.0,
        "proxy_err": 0.007106000557541847,
        "err": 146.7618408203125,
        "tr(WHW.T)": 20653.2265625,
        "mse": 9.515557394479401e-06,
        "bpp_sum": 73728,
        "bpp_loss_sum": 44567084.0,
        "direction": "col",
        "num_pixels": 16777216
    },
    "29_k.pt": {
        "W_hat": null,
        "bpp_loss": 2.652540445327759,
        "bpp": 0.0,
        "proxy_err": 0.005511431489139795,
        "err": 90.198974609375,
        "tr(WHW.T)": 16365.7978515625,
        "mse": 2.2022781195119023e-05,
        "bpp_sum": 73728,
        "bpp_loss_sum": 11199289.0,
        "direction": "col",
        "num_pixels": 4194304
    },
    "29_v.pt": {
        "W_hat": null,
        "bpp_loss": 2.6535637378692627,
        "bpp": 0.0,
        "proxy_err": 0.030274879187345505,
        "err": 25.74663543701172,
        "tr(WHW.T)": 850.4290161132812,
        "mse": 8.110988346743397e-06,
        "bpp_sum": 73728,
        "bpp_loss_sum": 11203581.0,
        "direction": "col",
        "num_pixels": 4194304
    },
    "29_o.pt": {
        "W_hat": null,
        "bpp_loss": 2.669851303100586,
        "bpp": 0.0,
        "proxy_err": 0.019422749057412148,
        "err": 60.26576614379883,
        "tr(WHW.T)": 3102.84423828125,
        "mse": 5.621465334115783e-06,
        "bpp_sum": 73728,
        "bpp_loss_sum": 44866400.0,
        "direction": "col",
        "num_pixels": 16777216
    },
    "29_up.pt": {
        "W_hat": null,
        "bpp_loss": 2.6722098759242465,
        "bpp": 0.0,
        "proxy_err": 0.021814871579408646,
        "err": 280.7248229980469,
        "tr(WHW.T)": 12868.5068359375,
        "mse": 5.144202077644877e-06,
        "bpp_sum": 73728,
        "bpp_loss_sum": 156986576.0,
        "direction": "col",
        "num_pixels": 58720256
    },
    "29_gate.pt": {
        "W_hat": null,
        "bpp_loss": 2.6540772574288503,
        "bpp": 0.0,
        "proxy_err": 0.011899427510797977,
        "err": 456.5152282714844,
        "tr(WHW.T)": 38364.46875,
        "mse": 8.187254934455268e-06,
        "bpp_sum": 73728,
        "bpp_loss_sum": 155921824.0,
        "direction": "col",
        "num_pixels": 58720256
    },
    "29_down.pt": {
        "W_hat": null,
        "bpp_loss": 2.6730591910226003,
        "bpp": 0.0,
        "proxy_err": 0.024277064949274063,
        "err": 181.36241149902344,
        "tr(WHW.T)": 7470.5244140625,
        "mse": 5.042870725446846e-06,
        "bpp_sum": 258048,
        "bpp_loss_sum": 157220768.0,
        "direction": "col",
        "num_pixels": 58720256
    },
    "30_q.pt": {
        "W_hat": null,
        "bpp_loss": 2.6418771743774414,
        "bpp": 0.0,
        "proxy_err": 0.005404491443186998,
        "err": 129.9814453125,
        "tr(WHW.T)": 24050.634765625,
        "mse": 8.524728400516324e-06,
        "bpp_sum": 73728,
        "bpp_loss_sum": 44397072.0,
        "direction": "col",
        "num_pixels": 16777216
    },
    "30_k.pt": {
        "W_hat": null,
        "bpp_loss": 2.6493093967437744,
        "bpp": 0.0,
        "proxy_err": 0.005571658723056316,
        "err": 78.17364501953125,
        "tr(WHW.T)": 14030.587890625,
        "mse": 1.6023253920138814e-05,
        "bpp_sum": 73728,
        "bpp_loss_sum": 11185737.0,
        "direction": "col",
        "num_pixels": 4194304
    },
    "30_v.pt": {
        "W_hat": null,
        "bpp_loss": 2.6542999744415283,
        "bpp": 0.0,
        "proxy_err": 0.03990280255675316,
        "err": 34.43854522705078,
        "tr(WHW.T)": 863.0608520507812,
        "mse": 1.158018312708009e-05,
        "bpp_sum": 73728,
        "bpp_loss_sum": 11206669.0,
        "direction": "col",
        "num_pixels": 4194304
    },
    "30_o.pt": {
        "W_hat": null,
        "bpp_loss": 2.669165849685669,
        "bpp": 0.0,
        "proxy_err": 0.01825850084424019,
        "err": 88.90384674072266,
        "tr(WHW.T)": 4869.17578125,
        "mse": 6.433510861825198e-06,
        "bpp_sum": 73728,
        "bpp_loss_sum": 44854900.0,
        "direction": "col",
        "num_pixels": 16777216
    },
    "30_up.pt": {
        "W_hat": null,
        "bpp_loss": 2.6706886291503906,
        "bpp": 0.0,
        "proxy_err": 0.014203814789652824,
        "err": 308.3818054199219,
        "tr(WHW.T)": 21711.1953125,
        "mse": 5.385584245232167e-06,
        "bpp_sum": 73728,
        "bpp_loss_sum": 156897248.0,
        "direction": "col",
        "num_pixels": 58720256
    },
    "30_gate.pt": {
        "W_hat": null,
        "bpp_loss": 2.6513568333217075,
        "bpp": 0.0,
        "proxy_err": 0.009724660776555538,
        "err": 505.23944091796875,
        "tr(WHW.T)": 51954.453125,
        "mse": 8.744463229959365e-06,
        "bpp_sum": 73728,
        "bpp_loss_sum": 155762080.0,
        "direction": "col",
        "num_pixels": 58720256
    },
    "30_down.pt": {
        "W_hat": null,
        "bpp_loss": 2.6716673714773997,
        "bpp": 0.0,
        "proxy_err": 0.015546109527349472,
        "err": 136.96401977539062,
        "tr(WHW.T)": 8810.1796875,
        "mse": 5.14928706252249e-06,
        "bpp_sum": 258048,
        "bpp_loss_sum": 157139040.0,
        "direction": "col",
        "num_pixels": 58720256
    },
    "31_q.pt": {
        "W_hat": null,
        "bpp_loss": 2.643303871154785,
        "bpp": 0.0,
        "proxy_err": 0.0042223380878567696,
        "err": 194.96923828125,
        "tr(WHW.T)": 46175.65625,
        "mse": 1.0398373888165224e-05,
        "bpp_sum": 73728,
        "bpp_loss_sum": 44421008.0,
        "direction": "col",
        "num_pixels": 16777216
    },
    "31_k.pt": {
        "W_hat": null,
        "bpp_loss": 2.6565566062927246,
        "bpp": 0.0,
        "proxy_err": 0.004942471161484718,
        "err": 101.1607437133789,
        "tr(WHW.T)": 20467.64453125,
        "mse": 1.9722672732314095e-05,
        "bpp_sum": 73728,
        "bpp_loss_sum": 11216134.0,
        "direction": "col",
        "num_pixels": 4194304
    },
    "31_v.pt": {
        "W_hat": null,
        "bpp_loss": 2.645479679107666,
        "bpp": 0.0,
        "proxy_err": 0.018625875934958458,
        "err": 33.68906784057617,
        "tr(WHW.T)": 1808.723876953125,
        "mse": 9.093004337046295e-06,
        "bpp_sum": 73728,
        "bpp_loss_sum": 11169674.0,
        "direction": "col",
        "num_pixels": 4194304
    },
    "31_o.pt": {
        "W_hat": null,
        "bpp_loss": 2.653575897216797,
        "bpp": 0.0,
        "proxy_err": 0.01754068396985531,
        "err": 38.827735900878906,
        "tr(WHW.T)": 2213.58154296875,
        "mse": 6.325726189970737e-06,
        "bpp_sum": 73728,
        "bpp_loss_sum": 44593344.0,
        "direction": "col",
        "num_pixels": 16777216
    },
    "31_up.pt": {
        "W_hat": null,
        "bpp_loss": 2.6645499638148715,
        "bpp": 0.0,
        "proxy_err": 0.00685182586312294,
        "err": 472.9092712402344,
        "tr(WHW.T)": 69019.453125,
        "mse": 7.219638064270839e-06,
        "bpp_sum": 73728,
        "bpp_loss_sum": 156536784.0,
        "direction": "col",
        "num_pixels": 58720256
    },
    "31_gate.pt": {
        "W_hat": null,
        "bpp_loss": 2.6513189588274275,
        "bpp": 0.0,
        "proxy_err": 0.005403419025242329,
        "err": 780.5375366210938,
        "tr(WHW.T)": 144452.53125,
        "mse": 1.1359425116097555e-05,
        "bpp_sum": 73728,
        "bpp_loss_sum": 155759856.0,
        "direction": "col",
        "num_pixels": 58720256
    },
    "31_down.pt": {
        "W_hat": null,
        "bpp_loss": 2.664180210658482,
        "bpp": 0.0,
        "proxy_err": 0.00814022682607174,
        "err": 81.07818603515625,
        "tr(WHW.T)": 9960.1875,
        "mse": 5.498837253981037e-06,
        "bpp_sum": 258048,
        "bpp_loss_sum": 156699392.0,
        "direction": "col",
        "num_pixels": 58720256
    }
}