{
    "bpp_loss": 6.001570573559514,
    "ppl": {
        "imagenet": [
            0.66378,
            0.86928
        ]
    },
    "num_pixels": 169869312,
    "config": {
        "quant_args": {
            "seed": 0,
            "num_cpu_threads": 8,
            "batch_size": 16,
            "devset_size": 384,
            "ctx_size": 4096,
            "save_path": "../hf_model_comp/comp_qtip/ckpt/google--siglip2-base-patch16-224/norm_search_ldlq64_seed1/lmbda10000",
            "in_hess_path": "../Wparam_dataset/quip_hess/siglip-base-patch16-224_512",
            "in_hess_eig_path": null,
            "whiten": false,
            "base_model": "/home/jgryu/workspace/weight_compression/Wparam_dataset/hf_model/google--siglip2-base-patch16-224",
            "sigma_reg": 0.01,
            "sigma_reg2": 0.01,
            "scale_override": -1,
            "use_fp64": false,
            "no_use_buffered": false,
            "sample_proc": 1,
            "lowmem_ldlq": false,
            "ft_lr": 3e-06,
            "ft_bs": 4,
            "ft_update_freq": 1,
            "ft_epochs": 0,
            "ft_valid_freq": 1,
            "ft_valid_size": 128,
            "ft_early_stop": 5,
            "ft_grad_ckpt": false,
            "skip_list": null,
            "attn_implementation": null,
            "bundle": true,
            "ql": true,
            "ql_path": null,
            "hesseigen": null,
            "gptq": false,
            "ldlq": true,
            "comp_model_path": "../NWC/checkpoint/nwc_ql/block_seq_ql_random_scaler_meta-llama--Meta-Llama-3-8B__col_1024_gaussian_padding.pt/M16/lmbda10000_rdloss_ql_size16_encdim512_M16_Q4_R0_m0_batch_size2048_total_iter200000_lr0.0001_seed100/best_loss_model_loss_11.43015_bpp_6.30844_MSE_0.00043_total_iter_200000.pth.tar",
            "direction": "col",
            "comp_batch_size": 64,
            "quip_tune_iters": 0,
            "rescale_WH": false,
            "rescale_WH_2": false,
            "incoh_mode": "none",
            "lora_rank": 0,
            "ql_invH": false,
            "use_train_scale": false,
            "layerwise_cdt": false,
            "ft_comp_model": false,
            "ft_comp_model2": false,
            "ft_comp_lmbda": null,
            "ft_comp_ep": null,
            "ft_comp_steps": null,
            "ft_comp_learning_rate": 0.0001,
            "ft_comp_aux_learning_rate": 0.001,
            "ft_train": false,
            "ft_train_dec": false,
            "ql_random_uniform": false,
            "ql_search": false,
            "ql_search_layer_name": null,
            "ql_search_layer_idx": "",
            "ql_search_value": null,
            "ql_search_r": null,
            "ql_tuned": false,
            "layerwise_scale": false,
            "layer_normalize": false,
            "channelwise_scale": false,
            "optim_code": false,
            "row_normalize": false,
            "row_normalize2": false,
            "col_normalize": false,
            "global_normalize": false,
            "normalization_search": true,
            "code_optim": false,
            "code_optim_it": false,
            "code_optim_lr": 0.005,
            "code_optim_lmbda": null,
            "code_optim_test": false,
            "code_optim_model": "nwc_ql_sga",
            "optim_qs": false,
            "loss": "rdloss_ql",
            "Q": 4,
            "use_codes": false,
            "qmap_uniform": null,
            "qmap_hessian": false,
            "qmap_hessian_ql": false,
            "qmap_alpha": false,
            "qmap_optim_iter": 5,
            "qmap_optim": false,
            "cnorm_optim": false,
            "rnorm_optim": false,
            "ft_rnorm": false,
            "ft_scale_cond0": false,
            "ft_metadata": false,
            "ft_Wr": false,
            "ft_y": false,
            "ft_bpp_loss": false,
            "scaleH": false,
            "smooth_scaleH_alpha": null,
            "lb_scaleH": null,
            "scaleHinv": false,
            "scale_std": null,
            "ste": false,
            "handcraft_mode": null,
            "quant_method": null,
            "group_sz": -1,
            "jp_quality": -1,
            "bpg_quality": -1,
            "webp_quality": -1,
            "nic_model": null,
            "nic_checkpoint": null,
            "nic_patch_size": -1,
            "nic_norm_patch_size": -1,
            "illm_quality": -1,
            "scale_cond0": false,
            "scale_cond_ub": null,
            "scale_cond": false,
            "fp_iter": false,
            "fp_iter_max": null,
            "fp_tol": 1e-05,
            "perlayer_ft_epochs": 0,
            "perlayer_ft_bs": 0,
            "perlayer_ft_lmbda": 0,
            "initialize_codec": false,
            "use_hyper": false,
            "patch": false,
            "ecsq": false,
            "R_target": null
        },
        "model_config": {
            "return_dict": true,
            "output_hidden_states": false,
            "torchscript": false,
            "dtype": "float32",
            "pruned_heads": {},
            "tie_word_embeddings": true,
            "chunk_size_feed_forward": 0,
            "is_encoder_decoder": false,
            "is_decoder": false,
            "cross_attention_hidden_size": null,
            "add_cross_attention": false,
            "tie_encoder_decoder": false,
            "architectures": [
                "SiglipModel"
            ],
            "finetuning_task": null,
            "id2label": {
                "0": "LABEL_0",
                "1": "LABEL_1"
            },
            "label2id": {
                "LABEL_0": 0,
                "LABEL_1": 1
            },
            "task_specific_params": null,
            "problem_type": null,
            "tokenizer_class": null,
            "prefix": null,
            "bos_token_id": null,
            "pad_token_id": null,
            "eos_token_id": null,
            "sep_token_id": null,
            "decoder_start_token_id": null,
            "max_length": 20,
            "min_length": 0,
            "do_sample": false,
            "early_stopping": false,
            "num_beams": 1,
            "temperature": 1.0,
            "top_k": 50,
            "top_p": 1.0,
            "typical_p": 1.0,
            "repetition_penalty": 1.0,
            "length_penalty": 1.0,
            "no_repeat_ngram_size": 0,
            "encoder_no_repeat_ngram_size": 0,
            "bad_words_ids": null,
            "num_return_sequences": 1,
            "output_scores": false,
            "return_dict_in_generate": false,
            "forced_bos_token_id": null,
            "forced_eos_token_id": null,
            "remove_invalid_values": false,
            "exponential_decay_length_penalty": null,
            "suppress_tokens": null,
            "begin_suppress_tokens": null,
            "num_beam_groups": 1,
            "diversity_penalty": 0.0,
            "_name_or_path": "/home/jgryu/workspace/weight_compression/Wparam_dataset/hf_model/google--siglip2-base-patch16-224",
            "transformers_version": "4.57.5",
            "initializer_factor": 1.0,
            "model_type": "siglip",
            "tf_legacy_loss": false,
            "use_bfloat16": false,
            "text_config": {
                "return_dict": true,
                "output_hidden_states": false,
                "torchscript": false,
                "dtype": null,
                "pruned_heads": {},
                "tie_word_embeddings": true,
                "chunk_size_feed_forward": 0,
                "is_encoder_decoder": false,
                "is_decoder": false,
                "cross_attention_hidden_size": null,
                "add_cross_attention": false,
                "tie_encoder_decoder": false,
                "architectures": null,
                "finetuning_task": null,
                "id2label": {
                    "0": "LABEL_0",
                    "1": "LABEL_1"
                },
                "label2id": {
                    "LABEL_0": 0,
                    "LABEL_1": 1
                },
                "task_specific_params": null,
                "problem_type": null,
                "tokenizer_class": null,
                "prefix": null,
                "bos_token_id": 49406,
                "pad_token_id": 1,
                "eos_token_id": 49407,
                "sep_token_id": null,
                "decoder_start_token_id": null,
                "max_length": 20,
                "min_length": 0,
                "do_sample": false,
                "early_stopping": false,
                "num_beams": 1,
                "temperature": 1.0,
                "top_k": 50,
                "top_p": 1.0,
                "typical_p": 1.0,
                "repetition_penalty": 1.0,
                "length_penalty": 1.0,
                "no_repeat_ngram_size": 0,
                "encoder_no_repeat_ngram_size": 0,
                "bad_words_ids": null,
                "num_return_sequences": 1,
                "output_scores": false,
                "return_dict_in_generate": false,
                "forced_bos_token_id": null,
                "forced_eos_token_id": null,
                "remove_invalid_values": false,
                "exponential_decay_length_penalty": null,
                "suppress_tokens": null,
                "begin_suppress_tokens": null,
                "num_beam_groups": 1,
                "diversity_penalty": 0.0,
                "_name_or_path": "",
                "model_type": "siglip_text_model",
                "tf_legacy_loss": false,
                "use_bfloat16": false,
                "vocab_size": 256000,
                "hidden_size": 768,
                "intermediate_size": 3072,
                "num_hidden_layers": 12,
                "num_attention_heads": 12,
                "max_position_embeddings": 64,
                "layer_norm_eps": 1e-06,
                "hidden_act": "gelu_pytorch_tanh",
                "attention_dropout": 0.0,
                "projection_size": 768,
                "output_attentions": false
            },
            "vision_config": {
                "return_dict": true,
                "output_hidden_states": false,
                "torchscript": false,
                "dtype": null,
                "pruned_heads": {},
                "tie_word_embeddings": true,
                "chunk_size_feed_forward": 0,
                "is_encoder_decoder": false,
                "is_decoder": false,
                "cross_attention_hidden_size": null,
                "add_cross_attention": false,
                "tie_encoder_decoder": false,
                "architectures": null,
                "finetuning_task": null,
                "id2label": {
                    "0": "LABEL_0",
                    "1": "LABEL_1"
                },
                "label2id": {
                    "LABEL_0": 0,
                    "LABEL_1": 1
                },
                "task_specific_params": null,
                "problem_type": null,
                "tokenizer_class": null,
                "prefix": null,
                "bos_token_id": null,
                "pad_token_id": null,
                "eos_token_id": null,
                "sep_token_id": null,
                "decoder_start_token_id": null,
                "max_length": 20,
                "min_length": 0,
                "do_sample": false,
                "early_stopping": false,
                "num_beams": 1,
                "temperature": 1.0,
                "top_k": 50,
                "top_p": 1.0,
                "typical_p": 1.0,
                "repetition_penalty": 1.0,
                "length_penalty": 1.0,
                "no_repeat_ngram_size": 0,
                "encoder_no_repeat_ngram_size": 0,
                "bad_words_ids": null,
                "num_return_sequences": 1,
                "output_scores": false,
                "return_dict_in_generate": false,
                "forced_bos_token_id": null,
                "forced_eos_token_id": null,
                "remove_invalid_values": false,
                "exponential_decay_length_penalty": null,
                "suppress_tokens": null,
                "begin_suppress_tokens": null,
                "num_beam_groups": 1,
                "diversity_penalty": 0.0,
                "_name_or_path": "",
                "model_type": "siglip_vision_model",
                "tf_legacy_loss": false,
                "use_bfloat16": false,
                "hidden_size": 768,
                "intermediate_size": 3072,
                "num_hidden_layers": 12,
                "num_attention_heads": 12,
                "num_channels": 3,
                "patch_size": 16,
                "image_size": 224,
                "attention_dropout": 0.0,
                "layer_norm_eps": 1e-06,
                "hidden_act": "gelu_pytorch_tanh",
                "output_attentions": false
            },
            "comp_params": {
                "ft_rnorm": false,
                "row_normalize": false,
                "col_normalize": false,
                "normalization_search": true
            },
            "output_attentions": false
        }
    },
    "text_0_q.pt": {
        "W_hat": null,
        "bpp_loss": 5.9772694905598955,
        "bpp": 0.0,
        "proxy_err": 0.00010370865493314341,
        "err": 0.08415231853723526,
        "tr(WHW.T)": 811.4300537109375,
        "mse": 7.286168397513393e-07,
        "mse_normed": 0.0007426301599480212,
        "bpp_sum": 26112,
        "bpp_loss_sum": 3551649.0,
        "direction": "col",
        "num_pixels": 589824
    },
    "text_0_k.pt": {
        "W_hat": null,
        "bpp_loss": 5.959488338894314,
        "bpp": 0.0,
        "proxy_err": 0.00010880585614359006,
        "err": 0.031218554824590683,
        "tr(WHW.T)": 286.9197998046875,
        "mse": 2.726870889091515e-07,
        "mse_normed": 0.0007326166378334165,
        "bpp_sum": 26112,
        "bpp_loss_sum": 3541161.25,
        "direction": "col",
        "num_pixels": 589824
    },
    "text_0_v.pt": {
        "W_hat": null,
        "bpp_loss": 5.979157341851129,
        "bpp": 0.0,
        "proxy_err": 0.00014339845802169293,
        "err": 0.03488247096538544,
        "tr(WHW.T)": 243.25555419921875,
        "mse": 3.033670168406388e-07,
        "mse_normed": 0.000738296948838979,
        "bpp_sum": 26112,
        "bpp_loss_sum": 3552762.5,
        "direction": "col",
        "num_pixels": 589824
    },
    "text_0_o.pt": {
        "W_hat": null,
        "bpp_loss": 5.980266994900173,
        "bpp": 0.0,
        "proxy_err": 0.00030795109341852367,
        "err": 0.07313203811645508,
        "tr(WHW.T)": 237.47940063476562,
        "mse": 2.4513434482287266e-07,
        "mse_normed": 0.0006145912338979542,
        "bpp_sum": 26112,
        "bpp_loss_sum": 3553417.0,
        "direction": "col",
        "num_pixels": 589824
    },
    "text_0_fc1.pt": {
        "W_hat": null,
        "bpp_loss": 5.973616706000434,
        "bpp": 0.0,
        "proxy_err": 0.00010196129733230919,
        "err": 0.132005974650383,
        "tr(WHW.T)": 1294.66748046875,
        "mse": 3.9488585912295093e-07,
        "mse_normed": 0.0007296015392057598,
        "bpp_sum": 26112,
        "bpp_loss_sum": 14119642.0,
        "direction": "col",
        "num_pixels": 2359296
    },
    "text_0_fc2.pt": {
        "W_hat": null,
        "bpp_loss": 5.979866027832031,
        "bpp": 0.0,
        "proxy_err": 3.841158468276262e-05,
        "err": 0.02772011049091816,
        "tr(WHW.T)": 721.66015625,
        "mse": 2.5344911591673736e-07,
        "mse_normed": 0.0007592060719616711,
        "bpp_sum": 30720,
        "bpp_loss_sum": 14138994.0,
        "direction": "col",
        "num_pixels": 2359296
    },
    "text_1_q.pt": {
        "W_hat": null,
        "bpp_loss": 5.979264153374566,
        "bpp": 0.0,
        "proxy_err": 0.00021547706273850054,
        "err": 0.08817856758832932,
        "tr(WHW.T)": 409.224853515625,
        "mse": 4.607157677583018e-07,
        "mse_normed": 0.0006470707594417036,
        "bpp_sum": 26112,
        "bpp_loss_sum": 3552825.5,
        "direction": "col",
        "num_pixels": 589824
    },
    "text_1_k.pt": {
        "W_hat": null,
        "bpp_loss": 5.977663675944011,
        "bpp": 0.0,
        "proxy_err": 0.00021051912335678935,
        "err": 0.0902409702539444,
        "tr(WHW.T)": 428.65924072265625,
        "mse": 4.72744574153694e-07,
        "mse_normed": 0.0006512656691484153,
        "bpp_sum": 26112,
        "bpp_loss_sum": 3551881.5,
        "direction": "col",
        "num_pixels": 589824
    },
    "text_1_v.pt": {
        "W_hat": null,
        "bpp_loss": 5.979617224799262,
        "bpp": 0.0,
        "proxy_err": 0.00020565268641803414,
        "err": 0.04108130931854248,
        "tr(WHW.T)": 199.7606201171875,
        "mse": 2.14861302083591e-07,
        "mse_normed": 0.0006493192631751299,
        "bpp_sum": 26112,
        "bpp_loss_sum": 3553033.75,
        "direction": "col",
        "num_pixels": 589824
    },
    "text_1_o.pt": {
        "W_hat": null,
        "bpp_loss": 5.980085160997179,
        "bpp": 0.0,
        "proxy_err": 0.00035947636933997273,
        "err": 0.06636790931224823,
        "tr(WHW.T)": 184.62384033203125,
        "mse": 1.8327394002426445e-07,
        "mse_normed": 0.0005879367818124592,
        "bpp_sum": 26112,
        "bpp_loss_sum": 3553309.75,
        "direction": "col",
        "num_pixels": 589824
    },
    "text_1_fc1.pt": {
        "W_hat": null,
        "bpp_loss": 5.9918802049424915,
        "bpp": 0.0,
        "proxy_err": 0.00017577657126821578,
        "err": 0.20029470324516296,
        "tr(WHW.T)": 1139.484619140625,
        "mse": 3.2163623586711765e-07,
        "mse_normed": 0.0006808766047470272,
        "bpp_sum": 26112,
        "bpp_loss_sum": 14162731.0,
        "direction": "col",
        "num_pixels": 2359296
    },
    "text_1_fc2.pt": {
        "W_hat": null,
        "bpp_loss": 5.9815784030490455,
        "bpp": 0.0,
        "proxy_err": 0.0001340554590569809,
        "err": 0.20554620027542114,
        "tr(WHW.T)": 1533.292236328125,
        "mse": 2.540186301303038e-07,
        "mse_normed": 0.0006787606398575008,
        "bpp_sum": 30720,
        "bpp_loss_sum": 14143034.0,
        "direction": "col",
        "num_pixels": 2359296
    },
    "text_2_q.pt": {
        "W_hat": null,
        "bpp_loss": 5.9754443698459205,
        "bpp": 0.0,
        "proxy_err": 0.00021177218877710402,
        "err": 0.07735186070203781,
        "tr(WHW.T)": 365.259765625,
        "mse": 4.0200279727287125e-07,
        "mse_normed": 0.0006325884605757892,
        "bpp_sum": 26112,
        "bpp_loss_sum": 3550572.5,
        "direction": "col",
        "num_pixels": 589824
    },
    "text_2_k.pt": {
        "W_hat": null,
        "bpp_loss": 5.978024800618489,
        "bpp": 0.0,
        "proxy_err": 0.00020949335885234177,
        "err": 0.08049943298101425,
        "tr(WHW.T)": 384.2576904296875,
        "mse": 4.2068677430506796e-07,
        "mse_normed": 0.0006350210751406848,
        "bpp_sum": 26112,
        "bpp_loss_sum": 3552094.5,
        "direction": "col",
        "num_pixels": 589824
    },
    "text_2_v.pt": {
        "W_hat": null,
        "bpp_loss": 5.978772481282552,
        "bpp": 0.0,
        "proxy_err": 0.00020615076937247068,
        "err": 0.039801549166440964,
        "tr(WHW.T)": 193.07009887695312,
        "mse": 2.0728917604628805e-07,
        "mse_normed": 0.0006330093601718545,
        "bpp_sum": 26112,
        "bpp_loss_sum": 3552535.5,
        "direction": "col",
        "num_pixels": 589824
    },
    "text_2_o.pt": {
        "W_hat": null,
        "bpp_loss": 5.9788928561740455,
        "bpp": 0.0,
        "proxy_err": 0.00036239545443095267,
        "err": 0.06614073365926743,
        "tr(WHW.T)": 182.50982666015625,
        "mse": 1.806270972792845e-07,
        "mse_normed": 0.0005835391348227859,
        "bpp_sum": 26112,
        "bpp_loss_sum": 3552606.5,
        "direction": "col",
        "num_pixels": 589824
    },
    "text_2_fc1.pt": {
        "W_hat": null,
        "bpp_loss": 5.990798102484809,
        "bpp": 0.0,
        "proxy_err": 0.0002078072284348309,
        "err": 0.23263844847679138,
        "tr(WHW.T)": 1119.4915771484375,
        "mse": 2.9750049179710913e-07,
        "mse_normed": 0.0006417998811230063,
        "bpp_sum": 26112,
        "bpp_loss_sum": 14160178.0,
        "direction": "col",
        "num_pixels": 2359296
    },
    "text_2_fc2.pt": {
        "W_hat": null,
        "bpp_loss": 5.980208926730686,
        "bpp": 0.0,
        "proxy_err": 0.00013108500570524484,
        "err": 0.23673930764198303,
        "tr(WHW.T)": 1805.998291015625,
        "mse": 2.659137123828259e-07,
        "mse_normed": 0.0006581828347407281,
        "bpp_sum": 30720,
        "bpp_loss_sum": 14139803.0,
        "direction": "col",
        "num_pixels": 2359296
    },
    "text_3_q.pt": {
        "W_hat": null,
        "bpp_loss": 5.9783579508463545,
        "bpp": 0.0,
        "proxy_err": 0.00020444938854780048,
        "err": 0.0748075395822525,
        "tr(WHW.T)": 365.8975830078125,
        "mse": 3.914027786322549e-07,
        "mse_normed": 0.0006338770035654306,
        "bpp_sum": 26112,
        "bpp_loss_sum": 3552291.0,
        "direction": "col",
        "num_pixels": 589824
    },
    "text_3_k.pt": {
        "W_hat": null,
        "bpp_loss": 5.977586534288195,
        "bpp": 0.0,
        "proxy_err": 0.00021068482601549476,
        "err": 0.07540512084960938,
        "tr(WHW.T)": 357.90484619140625,
        "mse": 3.965852783949231e-07,
        "mse_normed": 0.0006355353980325162,
        "bpp_sum": 26112,
        "bpp_loss_sum": 3551836.0,
        "direction": "col",
        "num_pixels": 589824
    },
    "text_3_v.pt": {
        "W_hat": null,
        "bpp_loss": 5.978401607937283,
        "bpp": 0.0,
        "proxy_err": 0.0002028896560659632,
        "err": 0.04203011468052864,
        "tr(WHW.T)": 207.15750122070312,
        "mse": 2.189028265320303e-07,
        "mse_normed": 0.0006333727505989373,
        "bpp_sum": 26112,
        "bpp_loss_sum": 3552316.75,
        "direction": "col",
        "num_pixels": 589824
    },
    "text_3_o.pt": {
        "W_hat": null,
        "bpp_loss": 5.978873358832465,
        "bpp": 0.0,
        "proxy_err": 0.00033979929867200553,
        "err": 0.06607124209403992,
        "tr(WHW.T)": 194.44195556640625,
        "mse": 2.0526455557501322e-07,
        "mse_normed": 0.0006231556762941182,
        "bpp_sum": 26112,
        "bpp_loss_sum": 3552595.0,
        "direction": "col",
        "num_pixels": 589824
    },
    "text_3_fc1.pt": {
        "W_hat": null,
        "bpp_loss": 5.989599439832899,
        "bpp": 0.0,
        "proxy_err": 0.00026076840003952384,
        "err": 0.2900591492652893,
        "tr(WHW.T)": 1112.32470703125,
        "mse": 2.8391019668561057e-07,
        "mse_normed": 0.0006113023264333606,
        "bpp_sum": 26112,
        "bpp_loss_sum": 14157350.0,
        "direction": "col",
        "num_pixels": 2359296
    },
    "text_3_fc2.pt": {
        "W_hat": null,
        "bpp_loss": 5.980825636121962,
        "bpp": 0.0,
        "proxy_err": 0.00012786359002348036,
        "err": 0.25107094645500183,
        "tr(WHW.T)": 1963.58447265625,
        "mse": 2.658013329437381e-07,
        "mse_normed": 0.0006446060142479837,
        "bpp_sum": 30720,
        "bpp_loss_sum": 14141258.0,
        "direction": "col",
        "num_pixels": 2359296
    },
    "text_4_q.pt": {
        "W_hat": null,
        "bpp_loss": 5.979464636908637,
        "bpp": 0.0,
        "proxy_err": 0.0002484579454176128,
        "err": 0.09040339291095734,
        "tr(WHW.T)": 363.85791015625,
        "mse": 3.8617079667346843e-07,
        "mse_normed": 0.0006219266797415912,
        "bpp_sum": 26112,
        "bpp_loss_sum": 3552943.75,
        "direction": "col",
        "num_pixels": 589824
    },
    "text_4_k.pt": {
        "W_hat": null,
        "bpp_loss": 5.978751712375217,
        "bpp": 0.0,
        "proxy_err": 0.0002462110423948616,
        "err": 0.09043130278587341,
        "tr(WHW.T)": 367.29180908203125,
        "mse": 3.873188916259096e-07,
        "mse_normed": 0.0006247276323847473,
        "bpp_sum": 26112,
        "bpp_loss_sum": 3552523.25,
        "direction": "col",
        "num_pixels": 589824
    },
    "text_4_v.pt": {
        "W_hat": null,
        "bpp_loss": 5.979760911729601,
        "bpp": 0.0,
        "proxy_err": 0.00023958436213433743,
        "err": 0.05166944861412048,
        "tr(WHW.T)": 215.66285705566406,
        "mse": 2.2197923499334138e-07,
        "mse_normed": 0.0006223814561963081,
        "bpp_sum": 26112,
        "bpp_loss_sum": 3553118.5,
        "direction": "col",
        "num_pixels": 589824
    },
    "text_4_o.pt": {
        "W_hat": null,
        "bpp_loss": 5.982059054904514,
        "bpp": 0.0,
        "proxy_err": 0.0003290484310127795,
        "err": 0.06844700127840042,
        "tr(WHW.T)": 208.0149688720703,
        "mse": 2.1897383817304217e-07,
        "mse_normed": 0.0006374166114255786,
        "bpp_sum": 26112,
        "bpp_loss_sum": 3554474.0,
        "direction": "col",
        "num_pixels": 589824
    },
    "text_4_fc1.pt": {
        "W_hat": null,
        "bpp_loss": 5.988563537597656,
        "bpp": 0.0,
        "proxy_err": 0.0002808996650855988,
        "err": 0.31486254930496216,
        "tr(WHW.T)": 1120.907470703125,
        "mse": 2.7885496933777176e-07,
        "mse_normed": 0.0006003162707202137,
        "bpp_sum": 26112,
        "bpp_loss_sum": 14154906.0,
        "direction": "col",
        "num_pixels": 2359296
    },
    "text_4_fc2.pt": {
        "W_hat": null,
        "bpp_loss": 5.98153813680013,
        "bpp": 0.0,
        "proxy_err": 0.00014800149074289948,
        "err": 0.27991026639938354,
        "tr(WHW.T)": 1891.2666015625,
        "mse": 2.627965329793369e-07,
        "mse_normed": 0.0006278659566305578,
        "bpp_sum": 30720,
        "bpp_loss_sum": 14142939.0,
        "direction": "col",
        "num_pixels": 2359296
    },
    "text_5_q.pt": {
        "W_hat": null,
        "bpp_loss": 5.977419535319011,
        "bpp": 0.0,
        "proxy_err": 0.00025935849407687783,
        "err": 0.08814415335655212,
        "tr(WHW.T)": 339.8545227050781,
        "mse": 3.6035160633218766e-07,
        "mse_normed": 0.0006152483401820064,
        "bpp_sum": 26112,
        "bpp_loss_sum": 3551737.5,
        "direction": "col",
        "num_pixels": 589824
    },
    "text_5_k.pt": {
        "W_hat": null,
        "bpp_loss": 5.97838634914822,
        "bpp": 0.0,
        "proxy_err": 0.0002615189296193421,
        "err": 0.08843989670276642,
        "tr(WHW.T)": 338.17779541015625,
        "mse": 3.6006946402267204e-07,
        "mse_normed": 0.0006169774569571018,
        "bpp_sum": 26112,
        "bpp_loss_sum": 3552307.75,
        "direction": "col",
        "num_pixels": 589824
    },
    "text_5_v.pt": {
        "W_hat": null,
        "bpp_loss": 5.979511260986328,
        "bpp": 0.0,
        "proxy_err": 0.0002523420553188771,
        "err": 0.05564907193183899,
        "tr(WHW.T)": 220.53030395507812,
        "mse": 2.2618310424604715e-07,
        "mse_normed": 0.0006196992471814156,
        "bpp_sum": 26112,
        "bpp_loss_sum": 3552971.25,
        "direction": "col",
        "num_pixels": 589824
    },
    "text_5_o.pt": {
        "W_hat": null,
        "bpp_loss": 5.97984144422743,
        "bpp": 0.0,
        "proxy_err": 0.00034149299608543515,
        "err": 0.07207560539245605,
        "tr(WHW.T)": 211.06027221679688,
        "mse": 2.2324820747599006e-07,
        "mse_normed": 0.0006304846028797328,
        "bpp_sum": 26112,
        "bpp_loss_sum": 3553166.0,
        "direction": "col",
        "num_pixels": 589824
    },
    "text_5_fc1.pt": {
        "W_hat": null,
        "bpp_loss": 5.987442864312066,
        "bpp": 0.0,
        "proxy_err": 0.00029523595003411174,
        "err": 0.3308757543563843,
        "tr(WHW.T)": 1120.71630859375,
        "mse": 2.762034512215905e-07,
        "mse_normed": 0.0005911352345719934,
        "bpp_sum": 26112,
        "bpp_loss_sum": 14152262.0,
        "direction": "col",
        "num_pixels": 2359296
    },
    "text_5_fc2.pt": {
        "W_hat": null,
        "bpp_loss": 5.981413099500868,
        "bpp": 0.0,
        "proxy_err": 0.00015747413272038102,
        "err": 0.30240553617477417,
        "tr(WHW.T)": 1920.3504638671875,
        "mse": 2.7495244125930185e-07,
        "mse_normed": 0.0006206464604474604,
        "bpp_sum": 30720,
        "bpp_loss_sum": 14142644.0,
        "direction": "col",
        "num_pixels": 2359296
    },
    "text_6_q.pt": {
        "W_hat": null,
        "bpp_loss": 5.979538387722439,
        "bpp": 0.0,
        "proxy_err": 0.0002852130273822695,
        "err": 0.09675033390522003,
        "tr(WHW.T)": 339.2212829589844,
        "mse": 3.583080854241416e-07,
        "mse_normed": 0.0006131371483206749,
        "bpp_sum": 26112,
        "bpp_loss_sum": 3552987.25,
        "direction": "col",
        "num_pixels": 589824
    },
    "text_6_k.pt": {
        "W_hat": null,
        "bpp_loss": 5.978672027587891,
        "bpp": 0.0,
        "proxy_err": 0.0002774391614366323,
        "err": 0.09731024503707886,
        "tr(WHW.T)": 350.74444580078125,
        "mse": 3.6066700204173685e-07,
        "mse_normed": 0.0006118994788266718,
        "bpp_sum": 26112,
        "bpp_loss_sum": 3552476.25,
        "direction": "col",
        "num_pixels": 589824
    },
    "text_6_v.pt": {
        "W_hat": null,
        "bpp_loss": 5.978279113769531,
        "bpp": 0.0,
        "proxy_err": 0.0002743454242590815,
        "err": 0.05898003652691841,
        "tr(WHW.T)": 214.9845733642578,
        "mse": 2.1806651773204067e-07,
        "mse_normed": 0.0006111452239565551,
        "bpp_sum": 26112,
        "bpp_loss_sum": 3552244.5,
        "direction": "col",
        "num_pixels": 589824
    },
    "text_6_o.pt": {
        "W_hat": null,
        "bpp_loss": 5.979981316460504,
        "bpp": 0.0,
        "proxy_err": 0.0003409452037885785,
        "err": 0.07009977102279663,
        "tr(WHW.T)": 205.60421752929688,
        "mse": 2.1577046993570548e-07,
        "mse_normed": 0.0006270732264965773,
        "bpp_sum": 26112,
        "bpp_loss_sum": 3553248.5,
        "direction": "col",
        "num_pixels": 589824
    },
    "text_6_fc1.pt": {
        "W_hat": null,
        "bpp_loss": 5.986427730984158,
        "bpp": 0.0,
        "proxy_err": 0.00030603393679484725,
        "err": 0.3436371088027954,
        "tr(WHW.T)": 1122.87255859375,
        "mse": 2.742605431649281e-07,
        "mse_normed": 0.0005864224513061345,
        "bpp_sum": 26112,
        "bpp_loss_sum": 14149867.0,
        "direction": "col",
        "num_pixels": 2359296
    },
    "text_6_fc2.pt": {
        "W_hat": null,
        "bpp_loss": 5.982024298773871,
        "bpp": 0.0,
        "proxy_err": 0.00015573557175230235,
        "err": 0.3244123160839081,
        "tr(WHW.T)": 2083.09716796875,
        "mse": 2.849211000466312e-07,
        "mse_normed": 0.0006147001986391842,
        "bpp_sum": 30720,
        "bpp_loss_sum": 14144086.0,
        "direction": "col",
        "num_pixels": 2359296
    },
    "text_7_q.pt": {
        "W_hat": null,
        "bpp_loss": 5.978253682454427,
        "bpp": 0.0,
        "proxy_err": 0.0002907439775299281,
        "err": 0.09809840470552444,
        "tr(WHW.T)": 337.40478515625,
        "mse": 3.467604869911156e-07,
        "mse_normed": 0.000603288528509438,
        "bpp_sum": 26112,
        "bpp_loss_sum": 3552229.5,
        "direction": "col",
        "num_pixels": 589824
    },
    "text_7_k.pt": {
        "W_hat": null,
        "bpp_loss": 5.978772905137804,
        "bpp": 0.0,
        "proxy_err": 0.00028784931055270135,
        "err": 0.09600818157196045,
        "tr(WHW.T)": 333.5362548828125,
        "mse": 3.409897715300758e-07,
        "mse_normed": 0.0006054115365259349,
        "bpp_sum": 26112,
        "bpp_loss_sum": 3552535.75,
        "direction": "col",
        "num_pixels": 589824
    },
    "text_7_v.pt": {
        "W_hat": null,
        "bpp_loss": 5.980093214246962,
        "bpp": 0.0,
        "proxy_err": 0.00028352506342343986,
        "err": 0.06689757853746414,
        "tr(WHW.T)": 235.94943237304688,
        "mse": 2.3590297359987744e-07,
        "mse_normed": 0.0006013992824591696,
        "bpp_sum": 26112,
        "bpp_loss_sum": 3553314.5,
        "direction": "col",
        "num_pixels": 589824
    },
    "text_7_o.pt": {
        "W_hat": null,
        "bpp_loss": 5.97999021742079,
        "bpp": 0.0,
        "proxy_err": 0.0003580974298529327,
        "err": 0.08027056604623795,
        "tr(WHW.T)": 224.158447265625,
        "mse": 2.227857009984291e-07,
        "mse_normed": 0.0005958583205938339,
        "bpp_sum": 26112,
        "bpp_loss_sum": 3553253.75,
        "direction": "col",
        "num_pixels": 589824
    },
    "text_7_fc1.pt": {
        "W_hat": null,
        "bpp_loss": 5.986967298719618,
        "bpp": 0.0,
        "proxy_err": 0.00030929598142392933,
        "err": 0.34463560581207275,
        "tr(WHW.T)": 1114.25830078125,
        "mse": 2.6886200998887944e-07,
        "mse_normed": 0.0005822494276799262,
        "bpp_sum": 26112,
        "bpp_loss_sum": 14151140.0,
        "direction": "col",
        "num_pixels": 2359296
    },
    "text_7_fc2.pt": {
        "W_hat": null,
        "bpp_loss": 5.982443067762587,
        "bpp": 0.0,
        "proxy_err": 0.00017802767979446799,
        "err": 0.3444405794143677,
        "tr(WHW.T)": 1934.758544921875,
        "mse": 2.944713344277261e-07,
        "mse_normed": 0.0006125180516391993,
        "bpp_sum": 30720,
        "bpp_loss_sum": 14145074.0,
        "direction": "col",
        "num_pixels": 2359296
    },
    "text_8_q.pt": {
        "W_hat": null,
        "bpp_loss": 5.9771241082085504,
        "bpp": 0.0,
        "proxy_err": 0.0002837232896126807,
        "err": 0.09029126167297363,
        "tr(WHW.T)": 318.237060546875,
        "mse": 3.216265440642019e-07,
        "mse_normed": 0.000607919879257679,
        "bpp_sum": 26112,
        "bpp_loss_sum": 3551563.25,
        "direction": "col",
        "num_pixels": 589824
    },
    "text_8_k.pt": {
        "W_hat": null,
        "bpp_loss": 5.978162129720052,
        "bpp": 0.0,
        "proxy_err": 0.0002862274704966694,
        "err": 0.0902249738574028,
        "tr(WHW.T)": 315.2212219238281,
        "mse": 3.2148031436918245e-07,
        "mse_normed": 0.0006043727626092732,
        "bpp_sum": 26112,
        "bpp_loss_sum": 3552175.5,
        "direction": "col",
        "num_pixels": 589824
    },
    "text_8_v.pt": {
        "W_hat": null,
        "bpp_loss": 5.979737599690755,
        "bpp": 0.0,
        "proxy_err": 0.00028503924841061234,
        "err": 0.0682200938463211,
        "tr(WHW.T)": 239.33580017089844,
        "mse": 2.4296380729538214e-07,
        "mse_normed": 0.0006070261588320136,
        "bpp_sum": 26112,
        "bpp_loss_sum": 3553104.75,
        "direction": "col",
        "num_pixels": 589824
    },
    "text_8_o.pt": {
        "W_hat": null,
        "bpp_loss": 5.9808328416612415,
        "bpp": 0.0,
        "proxy_err": 0.00036122463643550873,
        "err": 0.08166307210922241,
        "tr(WHW.T)": 226.07281494140625,
        "mse": 2.318584222393838e-07,
        "mse_normed": 0.0006063371547497809,
        "bpp_sum": 26112,
        "bpp_loss_sum": 3553750.75,
        "direction": "col",
        "num_pixels": 589824
    },
    "text_8_fc1.pt": {
        "W_hat": null,
        "bpp_loss": 5.98688464694553,
        "bpp": 0.0,
        "proxy_err": 0.00031020681490190327,
        "err": 0.34444618225097656,
        "tr(WHW.T)": 1110.3759765625,
        "mse": 2.6598283398016065e-07,
        "mse_normed": 0.0005769942654296756,
        "bpp_sum": 26112,
        "bpp_loss_sum": 14150945.0,
        "direction": "col",
        "num_pixels": 2359296
    },
    "text_8_fc2.pt": {
        "W_hat": null,
        "bpp_loss": 5.983772277832031,
        "bpp": 0.0,
        "proxy_err": 0.0001466292014811188,
        "err": 0.3649680018424988,
        "tr(WHW.T)": 2489.053955078125,
        "mse": 2.9983459626237163e-07,
        "mse_normed": 0.0006034864927642047,
        "bpp_sum": 30720,
        "bpp_loss_sum": 14148210.0,
        "direction": "col",
        "num_pixels": 2359296
    },
    "text_9_q.pt": {
        "W_hat": null,
        "bpp_loss": 5.978377448187934,
        "bpp": 0.0,
        "proxy_err": 0.0002924291475210339,
        "err": 0.09474611282348633,
        "tr(WHW.T)": 323.996826171875,
        "mse": 3.299266779777099e-07,
        "mse_normed": 0.0006053030956536531,
        "bpp_sum": 26112,
        "bpp_loss_sum": 3552302.5,
        "direction": "col",
        "num_pixels": 589824
    },
    "text_9_k.pt": {
        "W_hat": null,
        "bpp_loss": 5.978205786810981,
        "bpp": 0.0,
        "proxy_err": 0.00028883881168439984,
        "err": 0.09368039667606354,
        "tr(WHW.T)": 324.33453369140625,
        "mse": 3.2631660928927886e-07,
        "mse_normed": 0.0006059667794033885,
        "bpp_sum": 26112,
        "bpp_loss_sum": 3552201.25,
        "direction": "col",
        "num_pixels": 589824
    },
    "text_9_v.pt": {
        "W_hat": null,
        "bpp_loss": 5.978932698567708,
        "bpp": 0.0,
        "proxy_err": 0.00029112864285707474,
        "err": 0.0672311782836914,
        "tr(WHW.T)": 230.93289184570312,
        "mse": 2.3399691428949154e-07,
        "mse_normed": 0.0006068928632885218,
        "bpp_sum": 26112,
        "bpp_loss_sum": 3552630.0,
        "direction": "col",
        "num_pixels": 589824
    },
    "text_9_o.pt": {
        "W_hat": null,
        "bpp_loss": 5.977420383029514,
        "bpp": 0.0,
        "proxy_err": 0.00032965626451186836,
        "err": 0.07123740017414093,
        "tr(WHW.T)": 216.0959930419922,
        "mse": 2.392095268533012e-07,
        "mse_normed": 0.0006550946272909641,
        "bpp_sum": 26112,
        "bpp_loss_sum": 3551738.0,
        "direction": "col",
        "num_pixels": 589824
    },
    "text_9_fc1.pt": {
        "W_hat": null,
        "bpp_loss": 5.985235002305773,
        "bpp": 0.0,
        "proxy_err": 0.0003154475998599082,
        "err": 0.3423853814601898,
        "tr(WHW.T)": 1085.3953857421875,
        "mse": 2.598536639197846e-07,
        "mse_normed": 0.0005756140453740954,
        "bpp_sum": 26112,
        "bpp_loss_sum": 14147053.0,
        "direction": "col",
        "num_pixels": 2359296
    },
    "text_9_fc2.pt": {
        "W_hat": null,
        "bpp_loss": 5.983996073404948,
        "bpp": 0.0,
        "proxy_err": 0.00014906951400917023,
        "err": 0.33750826120376587,
        "tr(WHW.T)": 2264.099853515625,
        "mse": 2.9697307013520913e-07,
        "mse_normed": 0.0006116564618423581,
        "bpp_sum": 30720,
        "bpp_loss_sum": 14148738.0,
        "direction": "col",
        "num_pixels": 2359296
    },
    "text_10_q.pt": {
        "W_hat": null,
        "bpp_loss": 5.981625027126736,
        "bpp": 0.0,
        "proxy_err": 0.000258711603237316,
        "err": 0.07308177649974823,
        "tr(WHW.T)": 282.48358154296875,
        "mse": 2.903257438902074e-07,
        "mse_normed": 0.0006070358213037252,
        "bpp_sum": 26112,
        "bpp_loss_sum": 3554218.0,
        "direction": "col",
        "num_pixels": 589824
    },
    "text_10_k.pt": {
        "W_hat": null,
        "bpp_loss": 5.978599124484592,
        "bpp": 0.0,
        "proxy_err": 0.000253445643465966,
        "err": 0.07310374826192856,
        "tr(WHW.T)": 288.4395446777344,
        "mse": 2.8806022100980044e-07,
        "mse_normed": 0.0006087020155973732,
        "bpp_sum": 26112,
        "bpp_loss_sum": 3552433.25,
        "direction": "col",
        "num_pixels": 589824
    },
    "text_10_v.pt": {
        "W_hat": null,
        "bpp_loss": 5.9796295166015625,
        "bpp": 0.0,
        "proxy_err": 0.00026290983078069985,
        "err": 0.07054951786994934,
        "tr(WHW.T)": 268.34112548828125,
        "mse": 2.7730018814509094e-07,
        "mse_normed": 0.0006078335572965443,
        "bpp_sum": 26112,
        "bpp_loss_sum": 3553041.0,
        "direction": "col",
        "num_pixels": 589824
    },
    "text_10_o.pt": {
        "W_hat": null,
        "bpp_loss": 5.983297136094835,
        "bpp": 0.0,
        "proxy_err": 0.00035009862040169537,
        "err": 0.08959881961345673,
        "tr(WHW.T)": 255.9245147705078,
        "mse": 2.55030101925513e-07,
        "mse_normed": 0.000599756371229887,
        "bpp_sum": 26112,
        "bpp_loss_sum": 3555204.25,
        "direction": "col",
        "num_pixels": 589824
    },
    "text_10_fc1.pt": {
        "W_hat": null,
        "bpp_loss": 5.98513921101888,
        "bpp": 0.0,
        "proxy_err": 0.0003181244828738272,
        "err": 0.33655425906181335,
        "tr(WHW.T)": 1057.9326171875,
        "mse": 2.549313080635329e-07,
        "mse_normed": 0.0005771165015175939,
        "bpp_sum": 26112,
        "bpp_loss_sum": 14146827.0,
        "direction": "col",
        "num_pixels": 2359296
    },
    "text_10_fc2.pt": {
        "W_hat": null,
        "bpp_loss": 5.985276963975695,
        "bpp": 0.0,
        "proxy_err": 0.00011538791295606643,
        "err": 0.28254857659339905,
        "tr(WHW.T)": 2448.684326171875,
        "mse": 2.858504899450054e-07,
        "mse_normed": 0.0006134419818408787,
        "bpp_sum": 30720,
        "bpp_loss_sum": 14151760.0,
        "direction": "col",
        "num_pixels": 2359296
    },
    "text_11_q.pt": {
        "W_hat": null,
        "bpp_loss": 5.979592641194661,
        "bpp": 0.0,
        "proxy_err": 0.0002798285859171301,
        "err": 0.06282424926757812,
        "tr(WHW.T)": 224.509765625,
        "mse": 2.1990850029851572e-07,
        "mse_normed": 0.0005770064890384674,
        "bpp_sum": 26112,
        "bpp_loss_sum": 3553019.25,
        "direction": "col",
        "num_pixels": 589824
    },
    "text_11_k.pt": {
        "W_hat": null,
        "bpp_loss": 5.976062350802952,
        "bpp": 0.0,
        "proxy_err": 0.00027868611505255103,
        "err": 0.06213928014039993,
        "tr(WHW.T)": 222.9722900390625,
        "mse": 2.1816529738316603e-07,
        "mse_normed": 0.000578527629841119,
        "bpp_sum": 26112,
        "bpp_loss_sum": 3550937.0,
        "direction": "col",
        "num_pixels": 589824
    },
    "text_11_v.pt": {
        "W_hat": null,
        "bpp_loss": 5.9757537841796875,
        "bpp": 0.0,
        "proxy_err": 0.0002723615325521678,
        "err": 0.08828780055046082,
        "tr(WHW.T)": 324.1566467285156,
        "mse": 3.083286514993233e-07,
        "mse_normed": 0.0005755795864388347,
        "bpp_sum": 26112,
        "bpp_loss_sum": 3550755.0,
        "direction": "col",
        "num_pixels": 589824
    },
    "text_11_o.pt": {
        "W_hat": null,
        "bpp_loss": 5.978998396131727,
        "bpp": 0.0,
        "proxy_err": 0.0002656012657098472,
        "err": 0.07265922427177429,
        "tr(WHW.T)": 273.5650634765625,
        "mse": 3.6524500046652975e-07,
        "mse_normed": 0.0007679129485040903,
        "bpp_sum": 26112,
        "bpp_loss_sum": 3552668.75,
        "direction": "col",
        "num_pixels": 589824
    },
    "text_11_fc1.pt": {
        "W_hat": null,
        "bpp_loss": 5.987839168972439,
        "bpp": 0.0,
        "proxy_err": 0.000299275474390015,
        "err": 0.27596497535705566,
        "tr(WHW.T)": 922.1102294921875,
        "mse": 2.397021603428584e-07,
        "mse_normed": 0.0006138142198324203,
        "bpp_sum": 26112,
        "bpp_loss_sum": 14153197.0,
        "direction": "col",
        "num_pixels": 2359296
    },
    "text_11_fc2.pt": {
        "W_hat": null,
        "bpp_loss": 5.9910024007161455,
        "bpp": 0.0,
        "proxy_err": 2.42811565840384e-05,
        "err": 0.18854475021362305,
        "tr(WHW.T)": 7765.064453125,
        "mse": 2.396899105860939e-07,
        "mse_normed": 0.000678350159432739,
        "bpp_sum": 30720,
        "bpp_loss_sum": 14165268.0,
        "direction": "col",
        "num_pixels": 2359296
    },
    "vision_0_q.pt": {
        "W_hat": null,
        "bpp_loss": 5.889912923177083,
        "bpp": 0.0,
        "proxy_err": 0.00010207164450548589,
        "err": 0.14714497327804565,
        "tr(WHW.T)": 1441.585205078125,
        "mse": 2.5218998871423537e-06,
        "mse_normed": 0.001439514453522861,
        "bpp_sum": 26112,
        "bpp_loss_sum": 3500124.0,
        "direction": "col",
        "num_pixels": 589824
    },
    "vision_0_k.pt": {
        "W_hat": null,
        "bpp_loss": 5.896146138509114,
        "bpp": 0.0,
        "proxy_err": 0.00010364559420850128,
        "err": 0.15290021896362305,
        "tr(WHW.T)": 1475.2215576171875,
        "mse": 2.549317287048325e-06,
        "mse_normed": 0.0013741956790909171,
        "bpp_sum": 26112,
        "bpp_loss_sum": 3503800.5,
        "direction": "col",
        "num_pixels": 589824
    },
    "vision_0_v.pt": {
        "W_hat": null,
        "bpp_loss": 5.91067377726237,
        "bpp": 0.0,
        "proxy_err": 0.00013619163655675948,
        "err": 0.01975686475634575,
        "tr(WHW.T)": 145.066650390625,
        "mse": 3.367079841609666e-07,
        "mse_normed": 0.0013035796582698822,
        "bpp_sum": 26112,
        "bpp_loss_sum": 3512369.25,
        "direction": "col",
        "num_pixels": 589824
    },
    "vision_0_o.pt": {
        "W_hat": null,
        "bpp_loss": 5.955526140001085,
        "bpp": 0.0,
        "proxy_err": 0.0002278638130519539,
        "err": 0.0347195528447628,
        "tr(WHW.T)": 152.3697509765625,
        "mse": 2.467183151111385e-07,
        "mse_normed": 0.0008582414011470973,
        "bpp_sum": 26112,
        "bpp_loss_sum": 3538824.25,
        "direction": "col",
        "num_pixels": 589824
    },
    "vision_0_fc1.pt": {
        "W_hat": null,
        "bpp_loss": 5.955005645751953,
        "bpp": 0.0,
        "proxy_err": 0.00017098913667723536,
        "err": 0.19571568071842194,
        "tr(WHW.T)": 1144.60888671875,
        "mse": 7.336720955208875e-07,
        "mse_normed": 0.0014541109558194876,
        "bpp_sum": 99840,
        "bpp_loss_sum": 14149461.0,
        "direction": "col",
        "num_pixels": 2359296
    },
    "vision_0_fc2.pt": {
        "W_hat": null,
        "bpp_loss": 5.924012078179254,
        "bpp": 0.0,
        "proxy_err": 9.044195030583069e-05,
        "err": 0.11221331357955933,
        "tr(WHW.T)": 1240.721923828125,
        "mse": 2.50851741157021e-07,
        "mse_normed": 0.0007737454143352807,
        "bpp_sum": 30720,
        "bpp_loss_sum": 14007218.0,
        "direction": "col",
        "num_pixels": 2359296
    },
    "vision_1_q.pt": {
        "W_hat": null,
        "bpp_loss": 5.946516672770183,
        "bpp": 0.0,
        "proxy_err": 0.0001574740163050592,
        "err": 0.09380680322647095,
        "tr(WHW.T)": 595.697021484375,
        "mse": 9.525143127575575e-07,
        "mse_normed": 0.000992623157799244,
        "bpp_sum": 26112,
        "bpp_loss_sum": 3533510.25,
        "direction": "col",
        "num_pixels": 589824
    },
    "vision_1_k.pt": {
        "W_hat": null,
        "bpp_loss": 5.9286753336588545,
        "bpp": 0.0,
        "proxy_err": 0.00015569000970572233,
        "err": 0.08970606327056885,
        "tr(WHW.T)": 576.183837890625,
        "mse": 9.21889181881852e-07,
        "mse_normed": 0.0009847518522292376,
        "bpp_sum": 26112,
        "bpp_loss_sum": 3522987.0,
        "direction": "col",
        "num_pixels": 589824
    },
    "vision_1_v.pt": {
        "W_hat": null,
        "bpp_loss": 5.963271670871311,
        "bpp": 0.0,
        "proxy_err": 0.00015845218149479479,
        "err": 0.03966587036848068,
        "tr(WHW.T)": 250.3333740234375,
        "mse": 3.9604250900993065e-07,
        "mse_normed": 0.0009784208377823234,
        "bpp_sum": 26112,
        "bpp_loss_sum": 3543392.75,
        "direction": "col",
        "num_pixels": 589824
    },
    "vision_1_o.pt": {
        "W_hat": null,
        "bpp_loss": 5.97373792860243,
        "bpp": 0.0,
        "proxy_err": 0.00019625185814220458,
        "err": 0.03683681786060333,
        "tr(WHW.T)": 187.70175170898438,
        "mse": 2.2718839431945526e-07,
        "mse_normed": 0.0007198353414423764,
        "bpp_sum": 26112,
        "bpp_loss_sum": 3549566.0,
        "direction": "col",
        "num_pixels": 589824
    },
    "vision_1_fc1.pt": {
        "W_hat": null,
        "bpp_loss": 5.9741100735134545,
        "bpp": 0.0,
        "proxy_err": 0.00016603947733528912,
        "err": 0.16902627050876617,
        "tr(WHW.T)": 1017.9884643554688,
        "mse": 3.9376541849378555e-07,
        "mse_normed": 0.0008980183047242463,
        "bpp_sum": 99840,
        "bpp_loss_sum": 14194534.0,
        "direction": "col",
        "num_pixels": 2359296
    },
    "vision_1_fc2.pt": {
        "W_hat": null,
        "bpp_loss": 5.959815979003906,
        "bpp": 0.0,
        "proxy_err": 9.032590605784208e-05,
        "err": 0.12151176482439041,
        "tr(WHW.T)": 1345.25927734375,
        "mse": 1.8159987291710422e-07,
        "mse_normed": 0.0006753181223757565,
        "bpp_sum": 30720,
        "bpp_loss_sum": 14091690.0,
        "direction": "col",
        "num_pixels": 2359296
    },
    "vision_2_q.pt": {
        "W_hat": null,
        "bpp_loss": 5.970252143012153,
        "bpp": 0.0,
        "proxy_err": 0.00021143045159988105,
        "err": 0.08283625543117523,
        "tr(WHW.T)": 391.78961181640625,
        "mse": 4.803627575711289e-07,
        "mse_normed": 0.0007559828809462488,
        "bpp_sum": 26112,
        "bpp_loss_sum": 3547510.0,
        "direction": "col",
        "num_pixels": 589824
    },
    "vision_2_k.pt": {
        "W_hat": null,
        "bpp_loss": 5.958223130967882,
        "bpp": 0.0,
        "proxy_err": 0.0002104512823279947,
        "err": 0.07984332740306854,
        "tr(WHW.T)": 379.3910217285156,
        "mse": 4.636904122889973e-07,
        "mse_normed": 0.0007481404463760555,
        "bpp_sum": 26112,
        "bpp_loss_sum": 3540415.0,
        "direction": "col",
        "num_pixels": 589824
    },
    "vision_2_v.pt": {
        "W_hat": null,
        "bpp_loss": 5.971273634168837,
        "bpp": 0.0,
        "proxy_err": 0.0002206369099440053,
        "err": 0.04886772111058235,
        "tr(WHW.T)": 221.48480224609375,
        "mse": 2.812664376961038e-07,
        "mse_normed": 0.0007454002625308931,
        "bpp_sum": 26112,
        "bpp_loss_sum": 3548112.5,
        "direction": "col",
        "num_pixels": 589824
    },
    "vision_2_o.pt": {
        "W_hat": null,
        "bpp_loss": 5.977049085828993,
        "bpp": 0.0,
        "proxy_err": 0.00023261652677319944,
        "err": 0.043655890971422195,
        "tr(WHW.T)": 187.6732177734375,
        "mse": 2.0954318813437567e-07,
        "mse_normed": 0.0006860208231955767,
        "bpp_sum": 26112,
        "bpp_loss_sum": 3551519.0,
        "direction": "col",
        "num_pixels": 589824
    },
    "vision_2_fc1.pt": {
        "W_hat": null,
        "bpp_loss": 5.9796142578125,
        "bpp": 0.0,
        "proxy_err": 0.0002261620102217421,
        "err": 0.21800251305103302,
        "tr(WHW.T)": 963.921875,
        "mse": 2.765463307241589e-07,
        "mse_normed": 0.0006880113505758345,
        "bpp_sum": 26112,
        "bpp_loss_sum": 14133792.0,
        "direction": "col",
        "num_pixels": 2359296
    },
    "vision_2_fc2.pt": {
        "W_hat": null,
        "bpp_loss": 5.961060841878255,
        "bpp": 0.0,
        "proxy_err": 0.00017534467042423785,
        "err": 0.1352878212928772,
        "tr(WHW.T)": 771.5536499023438,
        "mse": 1.7198892976466595e-07,
        "mse_normed": 0.0006597143365070224,
        "bpp_sum": 30720,
        "bpp_loss_sum": 14094627.0,
        "direction": "col",
        "num_pixels": 2359296
    },
    "vision_3_q.pt": {
        "W_hat": null,
        "bpp_loss": 5.972273508707683,
        "bpp": 0.0,
        "proxy_err": 0.00024175974249374121,
        "err": 0.08125486969947815,
        "tr(WHW.T)": 336.09759521484375,
        "mse": 3.902146374912263e-07,
        "mse_normed": 0.0007075112662278116,
        "bpp_sum": 26112,
        "bpp_loss_sum": 3548702.25,
        "direction": "col",
        "num_pixels": 589824
    },
    "vision_3_k.pt": {
        "W_hat": null,
        "bpp_loss": 5.965076446533203,
        "bpp": 0.0,
        "proxy_err": 0.00023997171956580132,
        "err": 0.07732905447483063,
        "tr(WHW.T)": 322.24237060546875,
        "mse": 3.7322632806535694e-07,
        "mse_normed": 0.0007106193224899471,
        "bpp_sum": 26112,
        "bpp_loss_sum": 3544457.25,
        "direction": "col",
        "num_pixels": 589824
    },
    "vision_3_v.pt": {
        "W_hat": null,
        "bpp_loss": 5.973642985026042,
        "bpp": 0.0,
        "proxy_err": 0.00025172653840854764,
        "err": 0.057373739778995514,
        "tr(WHW.T)": 227.9208984375,
        "mse": 2.7319836704009504e-07,
        "mse_normed": 0.0007082980591803789,
        "bpp_sum": 26112,
        "bpp_loss_sum": 3549510.0,
        "direction": "col",
        "num_pixels": 589824
    },
    "vision_3_o.pt": {
        "W_hat": null,
        "bpp_loss": 5.979074266221788,
        "bpp": 0.0,
        "proxy_err": 0.0002802947710733861,
        "err": 0.05672409385442734,
        "tr(WHW.T)": 202.3730010986328,
        "mse": 2.1266164651478903e-07,
        "mse_normed": 0.0006411750218831003,
        "bpp_sum": 26112,
        "bpp_loss_sum": 3552713.5,
        "direction": "col",
        "num_pixels": 589824
    },
    "vision_3_fc1.pt": {
        "W_hat": null,
        "bpp_loss": 5.976105160183376,
        "bpp": 0.0,
        "proxy_err": 0.00021501313312910497,
        "err": 0.2193656861782074,
        "tr(WHW.T)": 1020.2431640625,
        "mse": 2.8834489285145537e-07,
        "mse_normed": 0.0006736016948707402,
        "bpp_sum": 99840,
        "bpp_loss_sum": 14199241.0,
        "direction": "col",
        "num_pixels": 2359296
    },
    "vision_3_fc2.pt": {
        "W_hat": null,
        "bpp_loss": 5.964048597547743,
        "bpp": 0.0,
        "proxy_err": 0.00019220284593757242,
        "err": 0.13866282999515533,
        "tr(WHW.T)": 721.4400634765625,
        "mse": 1.7160381560188398e-07,
        "mse_normed": 0.0006470023072324693,
        "bpp_sum": 30720,
        "bpp_loss_sum": 14101676.0,
        "direction": "col",
        "num_pixels": 2359296
    },
    "vision_4_q.pt": {
        "W_hat": null,
        "bpp_loss": 5.973738352457683,
        "bpp": 0.0,
        "proxy_err": 0.00025599668151699007,
        "err": 0.08652954548597336,
        "tr(WHW.T)": 338.01043701171875,
        "mse": 3.688798244638747e-07,
        "mse_normed": 0.0006642405060119927,
        "bpp_sum": 26112,
        "bpp_loss_sum": 3549566.25,
        "direction": "col",
        "num_pixels": 589824
    },
    "vision_4_k.pt": {
        "W_hat": null,
        "bpp_loss": 5.965443505181207,
        "bpp": 0.0,
        "proxy_err": 0.00025644636480137706,
        "err": 0.08072525262832642,
        "tr(WHW.T)": 314.7841491699219,
        "mse": 3.4371473134342523e-07,
        "mse_normed": 0.0006661344086751342,
        "bpp_sum": 26112,
        "bpp_loss_sum": 3544673.75,
        "direction": "col",
        "num_pixels": 589824
    },
    "vision_4_v.pt": {
        "W_hat": null,
        "bpp_loss": 5.974769168429905,
        "bpp": 0.0,
        "proxy_err": 0.0002680222678463906,
        "err": 0.055519796907901764,
        "tr(WHW.T)": 207.14620971679688,
        "mse": 2.3589379338773142e-07,
        "mse_normed": 0.0006630452699027956,
        "bpp_sum": 26112,
        "bpp_loss_sum": 3550174.25,
        "direction": "col",
        "num_pixels": 589824
    },
    "vision_4_o.pt": {
        "W_hat": null,
        "bpp_loss": 5.97676255967882,
        "bpp": 0.0,
        "proxy_err": 0.00021072094386909157,
        "err": 0.03893173485994339,
        "tr(WHW.T)": 184.75494384765625,
        "mse": 1.9946863005770865e-07,
        "mse_normed": 0.0006545346695929766,
        "bpp_sum": 26112,
        "bpp_loss_sum": 3551350.0,
        "direction": "col",
        "num_pixels": 589824
    },
    "vision_4_fc1.pt": {
        "W_hat": null,
        "bpp_loss": 5.982237921820746,
        "bpp": 0.0,
        "proxy_err": 0.00022110431746114045,
        "err": 0.22945362329483032,
        "tr(WHW.T)": 1037.7618408203125,
        "mse": 2.815581865434069e-07,
        "mse_normed": 0.0006475559202954173,
        "bpp_sum": 26112,
        "bpp_loss_sum": 14139982.0,
        "direction": "col",
        "num_pixels": 2359296
    },
    "vision_4_fc2.pt": {
        "W_hat": null,
        "bpp_loss": 5.967831081814236,
        "bpp": 0.0,
        "proxy_err": 0.0002103315491694957,
        "err": 0.15462914109230042,
        "tr(WHW.T)": 735.1685791015625,
        "mse": 1.800220132963659e-07,
        "mse_normed": 0.0006406098254956305,
        "bpp_sum": 30720,
        "bpp_loss_sum": 14110600.0,
        "direction": "col",
        "num_pixels": 2359296
    },
    "vision_5_q.pt": {
        "W_hat": null,
        "bpp_loss": 5.9752248128255205,
        "bpp": 0.0,
        "proxy_err": 0.00026242388412356377,
        "err": 0.09121698141098022,
        "tr(WHW.T)": 347.59405517578125,
        "mse": 3.8177753935997316e-07,
        "mse_normed": 0.0006560723413713276,
        "bpp_sum": 26112,
        "bpp_loss_sum": 3550443.0,
        "direction": "col",
        "num_pixels": 589824
    },
    "vision_5_k.pt": {
        "W_hat": null,
        "bpp_loss": 5.967068566216363,
        "bpp": 0.0,
        "proxy_err": 0.0002614858094602823,
        "err": 0.08413901925086975,
        "tr(WHW.T)": 321.7727966308594,
        "mse": 3.512414536999131e-07,
        "mse_normed": 0.0006588435498997569,
        "bpp_sum": 26112,
        "bpp_loss_sum": 3545632.25,
        "direction": "col",
        "num_pixels": 589824
    },
    "vision_5_v.pt": {
        "W_hat": null,
        "bpp_loss": 5.97526380750868,
        "bpp": 0.0,
        "proxy_err": 0.00026515661738812923,
        "err": 0.0549297109246254,
        "tr(WHW.T)": 207.15948486328125,
        "mse": 2.266807399564641e-07,
        "mse_normed": 0.0006583389476872981,
        "bpp_sum": 26112,
        "bpp_loss_sum": 3550466.0,
        "direction": "col",
        "num_pixels": 589824
    },
    "vision_5_o.pt": {
        "W_hat": null,
        "bpp_loss": 5.9798168606228295,
        "bpp": 0.0,
        "proxy_err": 0.00023844385577831417,
        "err": 0.04377066344022751,
        "tr(WHW.T)": 183.56800842285156,
        "mse": 2.059336594584238e-07,
        "mse_normed": 0.0006754727801308036,
        "bpp_sum": 26112,
        "bpp_loss_sum": 3553151.5,
        "direction": "col",
        "num_pixels": 589824
    },
    "vision_5_fc1.pt": {
        "W_hat": null,
        "bpp_loss": 5.950377570258246,
        "bpp": 0.0,
        "proxy_err": 0.00023675641568843275,
        "err": 0.2795119285583496,
        "tr(WHW.T)": 1180.588623046875,
        "mse": 3.1837387837185815e-07,
        "mse_normed": 0.0006292499601840973,
        "bpp_sum": 26112,
        "bpp_loss_sum": 14064814.0,
        "direction": "col",
        "num_pixels": 2359296
    },
    "vision_5_fc2.pt": {
        "W_hat": null,
        "bpp_loss": 5.969434102376302,
        "bpp": 0.0,
        "proxy_err": 0.0001355526619590819,
        "err": 0.10989204049110413,
        "tr(WHW.T)": 810.6962890625,
        "mse": 1.899670678540133e-07,
        "mse_normed": 0.0006259576184675097,
        "bpp_sum": 30720,
        "bpp_loss_sum": 14114382.0,
        "direction": "col",
        "num_pixels": 2359296
    },
    "vision_6_q.pt": {
        "W_hat": null,
        "bpp_loss": 5.977205064561632,
        "bpp": 0.0,
        "proxy_err": 0.0002875950012821704,
        "err": 0.08929421007633209,
        "tr(WHW.T)": 310.4859619140625,
        "mse": 3.376701158686046e-07,
        "mse_normed": 0.0006427699117921293,
        "bpp_sum": 26112,
        "bpp_loss_sum": 3551611.0,
        "direction": "col",
        "num_pixels": 589824
    },
    "vision_6_k.pt": {
        "W_hat": null,
        "bpp_loss": 5.9719115363226996,
        "bpp": 0.0,
        "proxy_err": 0.0002855116908904165,
        "err": 0.08280792832374573,
        "tr(WHW.T)": 290.0334167480469,
        "mse": 3.129285914837965e-07,
        "mse_normed": 0.000641173857729882,
        "bpp_sum": 26112,
        "bpp_loss_sum": 3548488.75,
        "direction": "col",
        "num_pixels": 589824
    },
    "vision_6_v.pt": {
        "W_hat": null,
        "bpp_loss": 5.974299960666233,
        "bpp": 0.0,
        "proxy_err": 0.00028814582037739456,
        "err": 0.06916588544845581,
        "tr(WHW.T)": 240.03778076171875,
        "mse": 2.6059146307488845e-07,
        "mse_normed": 0.0006464077741838992,
        "bpp_sum": 26112,
        "bpp_loss_sum": 3549897.5,
        "direction": "col",
        "num_pixels": 589824
    },
    "vision_6_o.pt": {
        "W_hat": null,
        "bpp_loss": 5.977935791015625,
        "bpp": 0.0,
        "proxy_err": 0.0002742723445408046,
        "err": 0.058227937668561935,
        "tr(WHW.T)": 212.29971313476562,
        "mse": 2.2275912670011166e-07,
        "mse_normed": 0.0006244556279852986,
        "bpp_sum": 26112,
        "bpp_loss_sum": 3552042.0,
        "direction": "col",
        "num_pixels": 589824
    },
    "vision_6_fc1.pt": {
        "W_hat": null,
        "bpp_loss": 5.984649658203125,
        "bpp": 0.0,
        "proxy_err": 0.0002770595019683242,
        "err": 0.2937833070755005,
        "tr(WHW.T)": 1060.36181640625,
        "mse": 2.7579628181229054e-07,
        "mse_normed": 0.0006193123990669847,
        "bpp_sum": 26112,
        "bpp_loss_sum": 14145672.0,
        "direction": "col",
        "num_pixels": 2359296
    },
    "vision_6_fc2.pt": {
        "W_hat": null,
        "bpp_loss": 5.970085991753472,
        "bpp": 0.0,
        "proxy_err": 0.00022463461209554225,
        "err": 0.24665242433547974,
        "tr(WHW.T)": 1098.01611328125,
        "mse": 2.5113050128311443e-07,
        "mse_normed": 0.0006315034115687013,
        "bpp_sum": 30720,
        "bpp_loss_sum": 14115920.0,
        "direction": "col",
        "num_pixels": 2359296
    },
    "vision_7_q.pt": {
        "W_hat": null,
        "bpp_loss": 5.9770151774088545,
        "bpp": 0.0,
        "proxy_err": 0.00029435334727168083,
        "err": 0.09146866947412491,
        "tr(WHW.T)": 310.74444580078125,
        "mse": 3.2735255217630765e-07,
        "mse_normed": 0.000634760654065758,
        "bpp_sum": 26112,
        "bpp_loss_sum": 3551499.0,
        "direction": "col",
        "num_pixels": 589824
    },
    "vision_7_k.pt": {
        "W_hat": null,
        "bpp_loss": 5.976186116536458,
        "bpp": 0.0,
        "proxy_err": 0.0002956835087388754,
        "err": 0.08885078132152557,
        "tr(WHW.T)": 300.49285888671875,
        "mse": 3.170725904055871e-07,
        "mse_normed": 0.000630529539193958,
        "bpp_sum": 26112,
        "bpp_loss_sum": 3551010.0,
        "direction": "col",
        "num_pixels": 589824
    },
    "vision_7_v.pt": {
        "W_hat": null,
        "bpp_loss": 5.976338280571832,
        "bpp": 0.0,
        "proxy_err": 0.000301629479508847,
        "err": 0.06771747767925262,
        "tr(WHW.T)": 224.50550842285156,
        "mse": 2.4145057864188857e-07,
        "mse_normed": 0.0006281054229475558,
        "bpp_sum": 26112,
        "bpp_loss_sum": 3551099.75,
        "direction": "col",
        "num_pixels": 589824
    },
    "vision_7_o.pt": {
        "W_hat": null,
        "bpp_loss": 5.980541653103298,
        "bpp": 0.0,
        "proxy_err": 0.00030445423908531666,
        "err": 0.06154790148139,
        "tr(WHW.T)": 202.1581268310547,
        "mse": 2.134842560508332e-07,
        "mse_normed": 0.0006163149373605847,
        "bpp_sum": 26112,
        "bpp_loss_sum": 3553579.0,
        "direction": "col",
        "num_pixels": 589824
    },
    "vision_7_fc1.pt": {
        "W_hat": null,
        "bpp_loss": 5.984934488932292,
        "bpp": 0.0,
        "proxy_err": 0.000296582787996158,
        "err": 0.29413914680480957,
        "tr(WHW.T)": 991.7606811523438,
        "mse": 2.500788980341895e-07,
        "mse_normed": 0.0006027066265232861,
        "bpp_sum": 26112,
        "bpp_loss_sum": 14146344.0,
        "direction": "col",
        "num_pixels": 2359296
    },
    "vision_7_fc2.pt": {
        "W_hat": null,
        "bpp_loss": 5.97455554538303,
        "bpp": 0.0,
        "proxy_err": 0.00026685488410294056,
        "err": 0.3310229182243347,
        "tr(WHW.T)": 1240.46044921875,
        "mse": 2.835791406141652e-07,
        "mse_normed": 0.0006054438999854028,
        "bpp_sum": 30720,
        "bpp_loss_sum": 14126465.0,
        "direction": "col",
        "num_pixels": 2359296
    },
    "vision_8_q.pt": {
        "W_hat": null,
        "bpp_loss": 5.977594587537977,
        "bpp": 0.0,
        "proxy_err": 0.00032803541398607194,
        "err": 0.09827083349227905,
        "tr(WHW.T)": 299.5738525390625,
        "mse": 3.0648814686173864e-07,
        "mse_normed": 0.0006027140188962221,
        "bpp_sum": 26112,
        "bpp_loss_sum": 3551840.75,
        "direction": "col",
        "num_pixels": 589824
    },
    "vision_8_k.pt": {
        "W_hat": null,
        "bpp_loss": 5.977358924018012,
        "bpp": 0.0,
        "proxy_err": 0.0003209809074178338,
        "err": 0.09746675193309784,
        "tr(WHW.T)": 303.6528015136719,
        "mse": 3.0507922588185465e-07,
        "mse_normed": 0.0006056468118913472,
        "bpp_sum": 26112,
        "bpp_loss_sum": 3551701.75,
        "direction": "col",
        "num_pixels": 589824
    },
    "vision_8_v.pt": {
        "W_hat": null,
        "bpp_loss": 5.977110544840495,
        "bpp": 0.0,
        "proxy_err": 0.00032872273004613817,
        "err": 0.08077709376811981,
        "tr(WHW.T)": 245.7301788330078,
        "mse": 2.53170952646542e-07,
        "mse_normed": 0.0006033602403476834,
        "bpp_sum": 26112,
        "bpp_loss_sum": 3551555.25,
        "direction": "col",
        "num_pixels": 589824
    },
    "vision_8_o.pt": {
        "W_hat": null,
        "bpp_loss": 5.981566111246745,
        "bpp": 0.0,
        "proxy_err": 0.0003401736612431705,
        "err": 0.07730133831501007,
        "tr(WHW.T)": 227.24081420898438,
        "mse": 2.3408554739035026e-07,
        "mse_normed": 0.0006136097363196313,
        "bpp_sum": 26112,
        "bpp_loss_sum": 3554183.25,
        "direction": "col",
        "num_pixels": 589824
    },
    "vision_8_fc1.pt": {
        "W_hat": null,
        "bpp_loss": 6.00067138671875,
        "bpp": 0.0,
        "proxy_err": 0.000325451313983649,
        "err": 0.3439991772174835,
        "tr(WHW.T)": 1056.9912109375,
        "mse": 2.6484659088055196e-07,
        "mse_normed": 0.0005969209014438093,
        "bpp_sum": 26112,
        "bpp_loss_sum": 14183472.0,
        "direction": "col",
        "num_pixels": 2359296
    },
    "vision_8_fc2.pt": {
        "W_hat": null,
        "bpp_loss": 5.982764773898655,
        "bpp": 0.0,
        "proxy_err": 0.00017376267351210117,
        "err": 0.3529243767261505,
        "tr(WHW.T)": 2031.0712890625,
        "mse": 2.6848547918234544e-07,
        "mse_normed": 0.0005932489293627441,
        "bpp_sum": 30720,
        "bpp_loss_sum": 14145833.0,
        "direction": "col",
        "num_pixels": 2359296
    },
    "vision_9_q.pt": {
        "W_hat": null,
        "bpp_loss": 5.980193244086371,
        "bpp": 0.0,
        "proxy_err": 0.00034296195372007787,
        "err": 0.09703509509563446,
        "tr(WHW.T)": 282.9325256347656,
        "mse": 2.82737971701863e-07,
        "mse_normed": 0.0005890563479624689,
        "bpp_sum": 26112,
        "bpp_loss_sum": 3553373.5,
        "direction": "col",
        "num_pixels": 589824
    },
    "vision_9_k.pt": {
        "W_hat": null,
        "bpp_loss": 5.977780659993489,
        "bpp": 0.0,
        "proxy_err": 0.00034388055792078376,
        "err": 0.09780736267566681,
        "tr(WHW.T)": 284.4224853515625,
        "mse": 2.8434129717425094e-07,
        "mse_normed": 0.0005865623825229704,
        "bpp_sum": 26112,
        "bpp_loss_sum": 3551950.5,
        "direction": "col",
        "num_pixels": 589824
    },
    "vision_9_v.pt": {
        "W_hat": null,
        "bpp_loss": 5.9805187649197045,
        "bpp": 0.0,
        "proxy_err": 0.00034495905856601894,
        "err": 0.10114607214927673,
        "tr(WHW.T)": 293.2118225097656,
        "mse": 2.9322941941245517e-07,
        "mse_normed": 0.000586321868468076,
        "bpp_sum": 26112,
        "bpp_loss_sum": 3553565.5,
        "direction": "col",
        "num_pixels": 589824
    },
    "vision_9_o.pt": {
        "W_hat": null,
        "bpp_loss": 5.9807760450575085,
        "bpp": 0.0,
        "proxy_err": 0.00036060556885786355,
        "err": 0.09844014793634415,
        "tr(WHW.T)": 272.98565673828125,
        "mse": 2.7821778303405154e-07,
        "mse_normed": 0.0006051217787899077,
        "bpp_sum": 26112,
        "bpp_loss_sum": 3553717.25,
        "direction": "col",
        "num_pixels": 589824
    },
    "vision_9_fc1.pt": {
        "W_hat": null,
        "bpp_loss": 5.981500413682726,
        "bpp": 0.0,
        "proxy_err": 0.00034736530506052077,
        "err": 0.3991090655326843,
        "tr(WHW.T)": 1148.960693359375,
        "mse": 2.749462169049366e-07,
        "mse_normed": 0.0005739378975704312,
        "bpp_sum": 26112,
        "bpp_loss_sum": 14138242.0,
        "direction": "col",
        "num_pixels": 2359296
    },
    "vision_9_fc2.pt": {
        "W_hat": null,
        "bpp_loss": 5.985944535997179,
        "bpp": 0.0,
        "proxy_err": 0.0003042076714336872,
        "err": 0.4438337981700897,
        "tr(WHW.T)": 1458.98291015625,
        "mse": 3.0294890507320815e-07,
        "mse_normed": 0.0005803583189845085,
        "bpp_sum": 30720,
        "bpp_loss_sum": 14153335.0,
        "direction": "col",
        "num_pixels": 2359296
    },
    "vision_10_q.pt": {
        "W_hat": null,
        "bpp_loss": 5.977356804741754,
        "bpp": 0.0,
        "proxy_err": 0.00034825713373720646,
        "err": 0.09804776310920715,
        "tr(WHW.T)": 281.5384216308594,
        "mse": 2.690193809939956e-07,
        "mse_normed": 0.0005694216233678162,
        "bpp_sum": 26112,
        "bpp_loss_sum": 3551700.5,
        "direction": "col",
        "num_pixels": 589824
    },
    "vision_10_k.pt": {
        "W_hat": null,
        "bpp_loss": 5.97323481241862,
        "bpp": 0.0,
        "proxy_err": 0.0003482384199742228,
        "err": 0.10054723173379898,
        "tr(WHW.T)": 288.73101806640625,
        "mse": 2.7622573384178395e-07,
        "mse_normed": 0.0005680902977474034,
        "bpp_sum": 26112,
        "bpp_loss_sum": 3549269.25,
        "direction": "col",
        "num_pixels": 589824
    },
    "vision_10_v.pt": {
        "W_hat": null,
        "bpp_loss": 5.978095160590278,
        "bpp": 0.0,
        "proxy_err": 0.00035366194788366556,
        "err": 0.120515838265419,
        "tr(WHW.T)": 340.765625,
        "mse": 3.3116253916887217e-07,
        "mse_normed": 0.0005696096923202276,
        "bpp_sum": 26112,
        "bpp_loss_sum": 3552136.0,
        "direction": "col",
        "num_pixels": 589824
    },
    "vision_10_o.pt": {
        "W_hat": null,
        "bpp_loss": 5.980035146077474,
        "bpp": 0.0,
        "proxy_err": 0.00034528973628766835,
        "err": 0.11225099861621857,
        "tr(WHW.T)": 325.0921936035156,
        "mse": 3.37483328394228e-07,
        "mse_normed": 0.0006134360446594656,
        "bpp_sum": 26112,
        "bpp_loss_sum": 3553280.25,
        "direction": "col",
        "num_pixels": 589824
    },
    "vision_10_fc1.pt": {
        "W_hat": null,
        "bpp_loss": 5.999607086181641,
        "bpp": 0.0,
        "proxy_err": 0.0003517895529512316,
        "err": 0.41358840465545654,
        "tr(WHW.T)": 1175.669921875,
        "mse": 2.744197615811572e-07,
        "mse_normed": 0.0005665178177878261,
        "bpp_sum": 26112,
        "bpp_loss_sum": 14180961.0,
        "direction": "col",
        "num_pixels": 2359296
    },
    "vision_10_fc2.pt": {
        "W_hat": null,
        "bpp_loss": 5.982543521457249,
        "bpp": 0.0,
        "proxy_err": 0.00028129082056693733,
        "err": 0.4898492097854614,
        "tr(WHW.T)": 1741.433349609375,
        "mse": 3.597013744638389e-07,
        "mse_normed": 0.0005964568699710071,
        "bpp_sum": 30720,
        "bpp_loss_sum": 14145311.0,
        "direction": "col",
        "num_pixels": 2359296
    },
    "vision_11_q.pt": {
        "W_hat": null,
        "bpp_loss": 5.9746593899197045,
        "bpp": 0.0,
        "proxy_err": 0.00033256644383072853,
        "err": 0.08438164740800858,
        "tr(WHW.T)": 253.7286834716797,
        "mse": 2.473955760251556e-07,
        "mse_normed": 0.0005725531373172998,
        "bpp_sum": 26112,
        "bpp_loss_sum": 3550109.5,
        "direction": "col",
        "num_pixels": 589824
    },
    "vision_11_k.pt": {
        "W_hat": null,
        "bpp_loss": 5.973919338650173,
        "bpp": 0.0,
        "proxy_err": 0.00032747077057138085,
        "err": 0.08791393786668777,
        "tr(WHW.T)": 268.4634704589844,
        "mse": 2.5822910743045213e-07,
        "mse_normed": 0.0005722814821638167,
        "bpp_sum": 26112,
        "bpp_loss_sum": 3549673.0,
        "direction": "col",
        "num_pixels": 589824
    },
    "vision_11_v.pt": {
        "W_hat": null,
        "bpp_loss": 5.976842668321398,
        "bpp": 0.0,
        "proxy_err": 0.00033550968510098755,
        "err": 0.1363963782787323,
        "tr(WHW.T)": 406.53485107421875,
        "mse": 3.9733862422508537e-07,
        "mse_normed": 0.0005712702986784279,
        "bpp_sum": 26112,
        "bpp_loss_sum": 3551397.25,
        "direction": "col",
        "num_pixels": 589824
    },
    "vision_11_o.pt": {
        "W_hat": null,
        "bpp_loss": 5.9794595506456165,
        "bpp": 0.0,
        "proxy_err": 0.0002849942829925567,
        "err": 0.11730575561523438,
        "tr(WHW.T)": 411.6073913574219,
        "mse": 4.287632009436493e-07,
        "mse_normed": 0.0006412158836610615,
        "bpp_sum": 26112,
        "bpp_loss_sum": 3552940.75,
        "direction": "col",
        "num_pixels": 589824
    },
    "vision_11_fc1.pt": {
        "W_hat": null,
        "bpp_loss": 6.000975714789496,
        "bpp": 0.0,
        "proxy_err": 0.000343125662766397,
        "err": 0.3901363015174866,
        "tr(WHW.T)": 1137.007080078125,
        "mse": 2.61590543004786e-07,
        "mse_normed": 0.0005659352173097432,
        "bpp_sum": 26112,
        "bpp_loss_sum": 14184190.0,
        "direction": "col",
        "num_pixels": 2359296
    },
    "vision_11_fc2.pt": {
        "W_hat": null,
        "bpp_loss": 5.971070183648004,
        "bpp": 0.0,
        "proxy_err": 0.00021932240633759648,
        "err": 0.43882033228874207,
        "tr(WHW.T)": 2000.80029296875,
        "mse": 3.6315321949587087e-07,
        "mse_normed": 0.000595934281591326,
        "bpp_sum": 30720,
        "bpp_loss_sum": 14118242.0,
        "direction": "col",
        "num_pixels": 2359296
    }
}